Workbook

Sheet TOC
D3: Table of Contents
D4: Full Service Offerings
D5: A&U
D6: Ad Testing
D7: Concept Testing
D8: Competitive Benchmarking
D9: Competitive Landscape / Market Landscape
D10: Message Testing w/ Max Diff
D11: Product Development w/ Conjoint
D12: Product Development w/ MaxDiff
D13: Segmentation
D15: Ad-Hoc Services
... D24: Jump to List View

Sheet Sheet2
D4: Main | E4: Booster | F4: Booster CPI
D5: 3205 | E5: =100*F5 -> 2926.6667 | F5: =878/30 -> 29.266667
D6: 3205 | E6: =100*F6 -> 2925 | F6: =585/20 -> 29.25
D7: 3205 | E7: =100*F7 -> 2927.5 | F7: =1171/40 -> 29.275
E8: =sum(D5:E7) -> 18394.167
E9: 500
E10: =E8+E9 -> 18894.167

Sheet Use Case Cost Overview & Calcul
D3: Cost Overview for Full-Service Research
B5: Base Full-Service Bundle Costs | D5: Tier 1 - Standard | E5: Tier 2 - Standard Plus | F5: Tier 3 - Advanced | G5: Tier 4 - Custom
B6: A&U | D6: ='A&U'!C35 -> $24,900 + n*(CPI*2.5+$0.68) | E6: ='A&U'!D35 -> $28,400 + n*(CPI*2.5+$0.68) | F6: ='A&U'!E35 -> $35,900 + n*(CPI*2.5+$0.68) | G6: ='A&U'!F35 -> Custom
B7: Ad Testing | D7: ='Ad Testing'!C36 -> $24,500 + n*(CPI*2.5+$0.68) | E7: ='Ad Testing'!D36 -> $27,000 + n*(CPI*2.5+$2.04) | F7: ='Ad Testing'!E36 -> $32,900 + n*(CPI*2.5+$2.04) | G7: ='Ad Testing'!F36 -> Custom
B8: Brand Tracking
B9: Concept Testing | D9: ='Concept Testing'!C35 -> $24,500 + n*(CPI*2.5+$0.68) | E9: ='Concept Testing'!D35 -> $27,000 + n*(CPI*2.5+$2.04) | F9: ='Concept Testing'!E35 -> $32,900 + n*(CPI*2.5+$2.04) | G9: ='Concept Testing'!F35 -> Custom
B10: Competitive Benchmarking | D10: ='Competitive Benchmarking'!C35 -> $32,000 + n*(CPI*2.5+$1.68) | E10: ='Competitive Benchmarking'!D35 -> $36,000 + n*(CPI*2.5+$3.04) | F10: ='Competitive Benchmarking'!E35 -> $48,500 + n*(CPI*2.5+$3.04) | G10: ='Competitive Benchmarking'!F35 -> Custom
B11: Competitive Landscape / Market Landscape | D11: ='Competitive Landscape Market L'!C35 -> $21,000 + n*(CPI*2.5+$0.68) | E11: ='Competitive Landscape Market L'!D35 -> $29,500 + n*(CPI*2.5+$0.68) | F11: ='Competitive Landscape Market L'!E35 -> $37,500 + n*(CPI*2.5+$0.68) | G11: ='Competitive Landscape Market L'!F35 -> Custom
B12: Message Testing w MaxDiff | D12: ='Message Testing w MaxDiff'!C35 -> $26,000 + n*(CPI*2.5) | E12: ='Message Testing w MaxDiff'!D35 -> $29,000 + n*(CPI*2.5) | F12: ='Message Testing w MaxDiff'!E35 -> $40,000 + n*(CPI*2.5) | G12: ='Message Testing w MaxDiff'!F35 -> Custom
B13: Product Development w Conjoint | D13: ='Product Development w Conjoint'!C35 -> $33,000 + n*(CPI*2.5) | E13: ='Product Development w Conjoint'!D35 -> $41,500 + n*(CPI*2.5) | F13: ='Product Development w Conjoint'!E35 -> $43,500 + n*(CPI*2.5) | G13: ='Product Development w Conjoint'!F35 -> Custom
B14: Product Development w MaxDiff | D14: ='Product Development w MaxDiff'!C35 -> $26,000 + n*(CPI*2.5) | E14: ='Product Development w MaxDiff'!D35 -> $29,000 + n*(CPI*2.5) | F14: ='Product Development w MaxDiff'!E35 -> $40,000 + n*(CPI*2.5) | G14: ='Product Development w MaxDiff'!F35 -> Custom
B15: Segmentation | D15: =Segmentation!C35 -> $57,750 + n*(CPI*2.5) | E15: =Segmentation!D35 | F15: =Segmentation!E35 | G15: =Segmentation!F35 -> Custom
B17: Data Collection Details
B18: Enter Cost per Complete (CPI) to Qualtrics | D18: 3 | E18: <-- Enter CPI from vendors
B19: Margin percentage | D19: 0.6 | E19: <-- Min 60%
B20: Cost per Complete (CPI) to Client | D20: =max(D18/(1-D19),5) -> 7.5 | E20: Note, minumum $5 CPI to clients
B22: Enter Sample Size (n) | D22: 2000 | E22: <-- Enter desired sample size
B24: Base Costs + Data Collection Costs | D24: Tier 1 - Standard | E24: Tier 2 - Standard Plus | F24: Tier 3 - Advanced | G24: Tier 4 - Custom
B25: A&U | D25: =D35+$D$22*($D$20+0.68) -> 41260 | E25: =E35+$D$22*($D$20+0.68) -> 44760 | F25: =F35+$D$22*($D$20+0.68) -> 52260 | G25: =G6 -> Custom
B26: Ad Testing | D26: =D36+$D$22*($D$20+0.68) -> 40860 | E26: =E36+$D$22*($D$20+2.04) -> 46080 | F26: =F36+$D$22*($D$20+2.04) -> 51980 | G26: =G7 -> Custom
B27: Concept Testing | D27: =D38+$D$22*($D$20+0.68) -> 40860 | E27: =E38+$D$22*($D$20+2.04) -> 46080 | F27: =F38+$D$22*($D$20+2.04) -> 51980 | G27: =G9 -> Custom
B28: Competitive Benchmarking | D28: =D39+$D$22*($D$20+1.68) -> 50360 | E28: =E39+$D$22*($D$20+3.04) -> 57080 | F28: =F39+$D$22*($D$20+3.04) -> 69580 | G28: =G10 -> Custom
B29: Competitive Landscape / Market Landscape | D29: =D40+$D$22*($D$20+0.68) -> 37360 | E29: =E40+$D$22*($D$20+0.68) -> 45860 | F29: =F40+$D$22*($D$20+0.68) -> 53860 | G29: =G11 -> Custom
B30: Message Testing w MaxDiff | D30: =D41+$D$22*($D$20) -> 41000 | E30: =E41+$D$22*($D$20) -> 44000 | F30: =F41+$D$22*($D$20) -> 55000 | G30: =G12 -> Custom
B31: Product Development w Conjoint | D31: =D42+$D$22*($D$20) -> 48000 | E31: =E42+$D$22*($D$20) -> 56500 | F31: =F42+$D$22*($D$20) -> 58500 | G31: =G13 -> Custom
B32: Product Development w MaxDiff | D32: =D43+$D$22*($D$20) -> 41000 | E32: =E43+$D$22*($D$20) -> 44000 | F32: =F43+$D$22*($D$20) -> 55000 | G32: =G14 -> Custom
B33: Segmentation | D33: =D44+$D$22*($D$20) -> 72750 | E33: - | F33: - | G33: =G15 -> Custom
B35: A&U | D35: =left(D6,7) -> $24,900 | E35: =LEFT(E6,7) -> $28,400 | F35: =LEFT(F6,7) -> $35,900
B36: AdTesting | D36: =left(D7,7) -> $24,500 | E36: =LEFT(E7,7) -> $27,000 | F36: =LEFT(F7,7) -> $32,900
B37: Brand Tracking | D37: =left(D8,7) | E37: =LEFT(E8,7) | F37: =LEFT(F8,7)
B38: Concept Testing | D38: =left(D9,7) -> $24,500 | E38: =LEFT(E9,7) -> $27,000 | F38: =LEFT(F9,7) -> $32,900
B39: Competitive Benchmarking | D39: =left(D10,7) -> $32,000 | E39: =LEFT(E10,7) -> $36,000 | F39: =LEFT(F10,7) -> $48,500
B40: Competitive Landscape / Market Landscape | D40: =left(D11,7) -> $21,000 | E40: =LEFT(E11,7) -> $29,500 | F40: =LEFT(F11,7) -> $37,500
B41: Message Testing w MaxDiff | D41: =left(D12,7) -> $26,000 | E41: =LEFT(E12,7) -> $29,000 | F41: =LEFT(F12,7) -> $40,000
B42: Product Development w Conjoint | D42: =left(D13,7) -> $33,000 | E42: =LEFT(E13,7) -> $41,500 | F42: =LEFT(F13,7) -> $43,500
B43: Product Development w MaxDiff | D43: =left(D14,7) -> $26,000 | E43: =LEFT(E14,7) -> $29,000 | F43: =LEFT(F14,7) -> $40,000
B44: Segmentation | D44: =left(D15,7) -> $57,750 | E44: =LEFT(E15,7) | F44: =LEFT(F15,7)
B46: Add-Ons or Ad-Hoc
B47: Total Costs of Add-Ons or Ad-Hoc | D47: =sum(H50,H71,H94,H123, H141,H153) -> 0
B49: Add-Ons or Ad-Hoc Services | D49: Service | E49: Tier | F49: Needed Details | G49: Entered Details | H49: Additional Costs
B50: Design and Build | G50: Total Additional Costs | H50: =sum(H63:H69) -> 0 | I50: =if((OR(C66=TRUE,C69=TRUE,C79=TRUE,C83=TRUE,C110=TRUE,C114=TRUE,C120=TRUE,C121=TRUE)=TRUE),"Plus custom quote estimate","")
C51: FALSE | D51: Survey Review and Consultation | E51: Standard | F51: Number Needed | G51: 1 | H51: =if(C51=TRUE,G51*2000,"")
C52: FALSE | D52: Survey Review and Consultation | E52: Standard Plus | F52: Number Needed | G52: 1 | H52: =if(C52=TRUE,G52*3000,"")
C53: FALSE | D53: Survey Review and Consultation | E53: Advanced | F53: Number Needed | G53: 1 | H53: =if(C53=TRUE,G53*5000,"")
C54: FALSE | D54: Survey Review and Consultation | E54: Custom | F54: =if(C54=TRUE,"Custom Quote Required","") | H54: =if(C54=TRUE,"Custom Quote Required","")
C55: FALSE | D55: Survey Design & Build | E55: Standard | F55: Number Needed | G55: 1 | H55: =if(C55=TRUE,G55*8000,"")
C56: FALSE | D56: Survey Design & Build | E56: Standard Plus | F56: Number Needed | G56: 1 | H56: =if(C56=TRUE,G56*10000,"")
C57: FALSE | D57: Survey Design & Build | E57: Advanced | F57: Number Needed | G57: 1 | H57: =if(C57=TRUE,G57*12000,"")
C58: FALSE | D58: Survey Design & Build | E58: Custom | F58: =if(C58=TRUE,"Custom Quote Required","") | H58: =if(C58=TRUE,"Custom Quote Required","")
C59: FALSE | D59: Survey Build (without Design) | E59: Standard | F59: Number Needed | G59: 1 | H59: =if(C59=TRUE,G59*1000,"")
C60: FALSE | D60: Survey Build (without Design) | E60: Standard Plus | F60: Number Needed | G60: 1 | H60: =if(C60=TRUE,G60*2500,"")
C61: FALSE | D61: Survey Build (without Design) | E61: Advanced | F61: Number Needed | G61: 1 | H61: =if(C61=TRUE,G61*5000,"")
C62: FALSE | D62: Survey Build (without Design) | E62: Custom | F62: =if(C62=TRUE,"Custom Quote Required","") | H62: =if(C62=TRUE,"Custom Quote Required","")
C63: FALSE | D63: Translation (front-end) | E63: Standard | F63: =if(C63=TRUE,"Number of Words (estimated)","") | G63: 1000 | H63: =if(C63=TRUE,G63*0.14,"")
C64: FALSE | D64: Translation (front-end) | E64: Standard Plus | F64: =IF(C64=TRUE,"Number of Words (estimated)","") | G64: 1000 | H64: =if(C64=TRUE,G64*0.53+125*roundup(G64/2500,0),"")
C65: FALSE | D65: Translation (front-end) | E65: Advanced | F65: =IF(C65=TRUE,"Number of Words (estimated)","") | G65: 1000 | H65: =if(C65=TRUE,G65*0.63+150*roundup(G65/2500,0),"")
C66: FALSE | D66: Translation (front-end) | E66: Custom | F66: =if(C66=TRUE,"Custom Quote Required","") | H66: =if(C66=TRUE,"Custom Quote Required","")
C67: FALSE | D67: Typing Tool Programming | E67: Standard | F67: =if(C67=TRUE,"Number of Typing Tools (1 is typical)","") | G67: 1 | H67: =if(C67=TRUE,G67*3000,"")
C68: FALSE | D68: Typing Tool Programming | E68: Standard Plus | F68: =IF(C68=TRUE,"Number of Typing Tools (1 is typical)","") | G68: 1 | H68: =if(C68=TRUE,G68*5000,"")
C69: FALSE | D69: Typing Tool Programming | E69: Custom | F69: =if(C69=TRUE,"Custom Quote Required","") | H69: =if(C69=TRUE,"Custom Quote Required","")
A70: Click "+" to expand and see Design and Build Add-Ons/Ad-Hoc Services
B71: Data Collection | G71: Total Additional Costs | H71: =sum(H73:H92) -> 0
C72: FALSE | D72: Panel Sample - Standard | E72: Standard | F72: =if(C72=TRUE,"Use CPI Calculator Above","") | H72: =if(C72=TRUE,0,"")
C73: FALSE | D73: Panel Sample | E73: Standard Plus | F73: =if(C73=TRUE,"Note, $1 extra per complete","") | H73: =if(C73=TRUE,$D$22,"")
C74: FALSE | D74: Panel Sample | E74: Advanced | F74: =if(C74=TRUE,"Note, $2 extra per complete","") | H74: =if(C74=TRUE,2*$D$22,"")
C75: FALSE | D75: Panel Sample - Probability Sample | E75: Standard | F75: =if(C75=TRUE,"Ensure CPI entered above is for Prob Sample","") | H75: =if(C75=TRUE,0,"")
C76: FALSE | D76: List Send - Branded | E76: Standard | F76: =if(C76=TRUE,"Number of List Send Services (1 is Typical)","") | G76: 1 | H76: =if(C76=TRUE,G76*1500,"")
C77: FALSE | D77: List Send - Branded | E77: Standard Plus | F77: =IF(C77=TRUE,"Number of List Send Services (1 is Typical)","") | G77: 1 | H77: =if(C77=TRUE,G77*3500,"")
C78: FALSE | D78: List Send - Branded | E78: Advanced | F78: =IF(C78=TRUE,"Number of List Send Services (1 is Typical)","") | G78: 1 | H78: =if(C78=TRUE,G78*7000,"")
C79: FALSE | D79: List Send - Branded | E79: Custom | F79: =if(C79=TRUE,"Custom Quote Required","") | H79: =if(C79=TRUE,"Custom Quote Required","")
C80: FALSE | D80: List Send - Unbranded | E80: Standard | F80: =if(C80=TRUE,"Number of List Send Services (1 is Typical)","") | G80: 1 | H80: =if(C80=TRUE,G80*2500,"") | I80: =if(C80=TRUE,"Must ensure they have an unbranded Brand ID set-up","")
C81: FALSE | D81: List Send - Unbranded | E81: Standard Plus | F81: =IF(C81=TRUE,"Number of List Send Services (1 is Typical)","") | G81: 1 | H81: =if(C81=TRUE,G81*4000,"") | I81: =if(C81=TRUE,"Must ensure they have an unbranded Brand ID set-up","")
C82: FALSE | D82: List Send - Unbranded | E82: Advanced | F82: =IF(C82=TRUE,"Number of List Send Services (1 is Typical)","") | G82: 1 | H82: =if(C82=TRUE,G82*7500,"") | I82: =if(C82=TRUE,"Must ensure they have an unbranded Brand ID set-up","")
C83: FALSE | D83: List Send - Unbranded | E83: Custom | F83: =if(C83=TRUE,"Custom Quote Required","") | H83: =if(C83=TRUE,"Custom Quote Required","")
C84: FALSE | D84: Incentive Management | E84: Standard | F84: =if(C84=TRUE,"Incentive Amount","") | G84: 15 | H84: =if(C84=TRUE,Max(1500,G84*D22*0.15)) -> FALSE | I84: =if(C84=TRUE,"Must be selected with Incentives","")
C85: FALSE | D85: Incentives | E85: Standard | F85: Number of Incentives | G85: 500 | H85: =if(C85=TRUE,G84*G85) -> FALSE | I85: =if(C85=TRUE,"Must be selected with Incentive Management","")
C86: FALSE | D86: 3rd Party Integration | E86: Standard | F86: =if(C86=TRUE,"Number of Integrations (1 is Typical)","") | G86: 1 | H86: =if(C86=TRUE,G86*1500,"")
C87: FALSE | D87: 3rd Party Integration | E87: Standard Plus | F87: =IF(C87=TRUE,"Number of Integrations (1 is Typical)","") | G87: 1 | H87: =if(C87=TRUE,G87*3000,"")
C88: FALSE | D88: 3rd Party Integration | E88: Advanced | F88: =IF(C88=TRUE,"Number of Integrations (1 is Typical)","") | G88: 1 | H88: =if(C88=TRUE,G88*5000,"")
C89: FALSE | D89: Data Appends | E89: Standard | F89: =if(C89=TRUE,"Number of Append Iterations (1 if only at end)","") | G89: 1 | H89: =if(C89=TRUE,G89*1000,"") | I89: =if(C89=TRUE,"Must use Lucid or Dynata","")
C90: FALSE | D90: Data Appends | E90: Standard Plus | F90: =IF(C90=TRUE,"Number of Append Iterations (1 if only at end)","") | G90: 1 | H90: =if(C90=TRUE,G90*2500,"") | I90: =IF(C90=TRUE,"Must use Lucid or Dynata","")
C91: FALSE | D91: Data Appends | E91: Advanced | F91: =if(C91=TRUE,"Number of Variable Sets Appending","") | G91: 1 | H91: =if(C91=TRUE,G91*3750,"") | I91: =if(C91=TRUE,"Must use Dynata","")
C92: FALSE | D92: Data Appends | E92: Custom | F92: =IF(C92=TRUE,"Number of Variable Sets Appending","") | G92: 1 | H92: =if(C92=TRUE,G92*6500,"") | I92: =IF(C92=TRUE,"Must use Dynata","")
A93: Click "+" to expand and see Data Collection Add-Ons/Ad-Hoc Services
B94: Reporting & Analytics | G94: Total Additional Costs | H94: =sum(H95:H109) -> 0
C95: FALSE | D95: Weighting | E95: Standard | F95: =if(C95=TRUE,"Number of Weight Variables Needed","") | G95: 1 | H95: =if(C95=TRUE,G95*6500,"") | I95: needs to be updated
C96: FALSE | D96: Weighting | E96: Standard Plus | F96: =IF(C96=TRUE,"Number of Weight Variables Needed","") | G96: 1 | H96: =IF(C96=TRUE,G96*6500,"") | I96: needs to be updated
C97: FALSE | D97: Weighting | E97: Advanced | F97: =IF(C97=TRUE,"Number of Weight Variables Needed","") | G97: 1 | H97: =IF(C97=TRUE,G97*6500,"") | I97: needs to be updated
C98: FALSE | D98: Weighting | E98: Custom | F98: =IF(C98=TRUE,"Number of Weight Variables Needed","") | G98: 1 | H98: =IF(C98=TRUE,G98*6500,"") | I98: needs to be updated
C99: FALSE | D99: Crosstabs | E99: Standard | H99: =if(C99=TRUE,1400,"")
C100: FALSE | D100: Crosstabs | E100: Standard Plus | H100: =if(C100=TRUE,2400,"")
C101: FALSE | D101: Crosstabs | E101: Advanced | H101: =if(C101=TRUE,3000,"")
C102: FALSE | D102: Crosstabs | E102: Custom | F102: =if(C102=TRUE,"Custom Quote Required","") | H102: =if(C102=TRUE,"Custom Quote Required","")
C103: FALSE | D103: Reporting | E103: Standard | H103: =if(C103=TRUE,10000,"")
C104: FALSE | D104: Reporting | E104: Standard Plus | H104: =if(C104=TRUE,15000,"")
C105: FALSE | D105: Reporting | E105: Advanced | H105: =if(C105=TRUE,20000,"")
C106: FALSE | D106: Reporting | E106: Custom | F106: =if(C106=TRUE,"Custom Quote Required","") | H106: =if(C106=TRUE,"Custom Quote Required","")
C107: FALSE | D107: Dashboards | E107: Standard | H107: =if(C107=TRUE,5000,"")
C108: FALSE | D108: Dashboards | E108: Standard Plus | H108: =if(C108=TRUE,10000,"")
C109: FALSE | D109: Dashboards | E109: Advanced | H109: =if(C109=TRUE,20000,"")
...

Sheet A&U
A3: A&U | B3: A&U One- Pager | C3: Fundamental research aimed to guide brand development business growth by better understanding a market and identifying opportunities to expand reach, attract new consumers, improve brand/product positioning, and optimize product and service features. | G3: Return to Home
B6: XM Solution | C6: Tier 1 - Standard | D6: Tier 2 - Standard Plus | E6: Tier 3 - Advanced | F6: Tier 4 - Custom
A7: Overview | B7: N/A | C7: Smaller | D7: Added imagery and reporting | E7: More brands, imagery, more reporting, regression analysis
A9: Design and Build | C9: Survey Design & Build - Standard | D9: Survey Design & Build - Standard Plus | E9: Survey Design & Build - Advanced
C10: Up to 8 competitor brands | D10: Up to 8 competitor brands | E10: Up to 15 competitor brands
C11: Up to 10 imagery statements | D11: Up to 20 imagery statements | E11: Up to 20 imagery statements
C12: No translation | D12: No translation | E12: No translation
C13: No typing tool programmed | D13: No typing tool programmed | E13: No typing tool programmed
B18: - | C18: 8000 | D18: 11500 | E18: 14000 | F18: Custom
A20: Data Collection | C20: B2B or B2C Sample through Online Panel Partners with up to 3 quotas on completes | D20: B2B or B2C Sample through Online Panel Partners with up to 3 quotas on completes | E20: B2B or B2C Sample through Online Panel Partners with up to 3 quotas on completes | F20: B2B or B2C Sample through Online Panel Partners with up to 3 quotas on completes
B22: - | C22: CPI * 2.5 / complete | D22: CPI * 2.5 / complete | E22: CPI * 2.5 / complete | F22: CPI * 2.5 / complete
A24: Analysis & Reporting | C24: Reporting - Standard Plus | D24: Reporting - Standard Plus | E24: Reporting - Advanced
C25: Data Scrub - Standard | D25: Data Scrub - Standard | E25: Data Scrub - Standard
C26: Crosstabs - Standard | D26: Crosstabs - Standard | E26: Crosstabs - Standard
C27: No Dashboard | D27: No Dashboard | E27: No Dashboard
C28: No Typing Tool | D28: No Typing Tool | E28: No Typing Tool
C29: Open-Ended coding - Standard Plus, for 1 OE per Person | D29: Open-Ended coding - Standard Plus, for 1 OE per Person | E29: Open-Ended coding - Standard Plus, for 1 OE per Person
C30: No Weighting | D30: No Weighting | E30: No Weighting
C31: No Regression Analysis | D31: No Regression Analysis | E31: Optional Regression Analysis
C32: No market sizing analysis | D32: No market sizing analysis | E32: No market sizing analysis
B33: - | C33: $16,900 + $0.68 * n (for OE coding) | D33: $16,900 + $0.68 * n (for OE coding) | E33: $21,900 + $0.68 * n (for OE coding) | F33: Custom
A35: Total Base Costs | B35: - | C35: $24,900 + n*(CPI*2.5+$0.68) | D35: $28,400 + n*(CPI*2.5+$0.68) | E35: $35,900 + n*(CPI*2.5+$0.68) | F35: Custom
B37: Optional Add-Ons
B38: Item | C38: Description | D38: Added Costs
B40: Market Sizing Analysis | D40: 2000
B41: Luth Passive Metering
B42: MFour Behavioral Data
B43: Data Append - Advanced
B44: Data Append - Extra Advanced
B45: Translations - Standard Plus
B46: Translations - Advanced
B47: Data Collection - Standard Plus | D47: Add $1 / Complete
B48: Data Collection - Advanced | D48: Add $2 / Complete
B49: Open-Ended Coding - Standard Plus
B50: Back-End Translations - Standard Plus
B51: Back-End Translations - Advanced
B52: Data Weighting - Standard
B53: Data Weighting - Standard Plus
B54: Data Weighting - Advanced
B55: Typing Tool Programming - Standard | D55: 3000
B56: Typing Tool Programming - Standard Plus | D56: 5000
B57: VoxPopMe Video Open Ends

Sheet Ad Testing
A3: Ad Testing | B3: Ad Testing One- Pager | C3: Testing advertisements, messaging, and content before it goes live in the market to mitigate the risk of an ineffective ad and ensure resonation with desired target audience. | G3: Return to Home
B6: XM Solution | C6: Tier 1 - Standard | D6: Tier 2 - Standard Plus | E6: Tier 3 - Advanced | F6: Tier 4 - Custom
A7: Overview | B7: =HYPERLINK("https://www.qualtrics.com/marketplace/creative-testing-study/","https://www.qualtrics.com/marketplace/advertising-creative-testing/") -> https://www.qualtrics.com/marketplace/advertising-creative-testing/ | C7: Ad Testing with Basic Reporting on a Smaller Set of Ads | D7: Ad Testing for a Larger Number of Ads | E7: Ad Testing with Additional Reporting | F7: Ad Testing with Custom Build Needs, Additional Analytics or Added Deliverables
B8: =HYPERLINK("https://www.qualtrics.com/marketplace/advertising-creative-testing/","https://www.qualtrics.com/marketplace/advertising-creative-testing/") -> https://www.qualtrics.com/marketplace/advertising-creative-testing/
A10: Design and Build | B10: An expert-built template preloaded with the right questions | C10: Survey Design & Build - Standard Plus | D10: Survey Design & Build - Advanced | E10: Survey Design & Build - Advanced
B11: Ph.D. designed methodology | C11: Sequential or Monadic Design | D11: Sequential or Monadic Design | E11: Sequential or Monadic Design
B12: Prebuilt logic and survey structure | C12: Up to 4 Ads (print ads or video ads) | D12: Up to 8 Ads (print ads or video ads) | E12: Up to 8 Ads (print ads or video ads)
B13: Automated workflow | C13: No translation | D13: No translation | E13: No translation
C14: No typing tool programmed | D14: No typing tool programmed | E14: No typing tool programmed
C15: Optional use of heatmap, hotspot, or highlighter tools | D15: Optional use of heatmap, hotspot, or highlighter tools | E15: Optional use of heatmap, hotspot, or highlighter tools
C16: Client must host videos or place on Vimeo/YouTube | D16: Client must host videos or place on Vimeo/YouTube | E16: Client must host videos or place on Vimeo/YouTube
B17: Creative Testing: Additional Fee Require License: Research Core 5
B19: Ad Creative Testing: Included in License Require License: Research Core 3 | C19: 11500 | D19: 14000 | E19: 14000 | F19: Custom
A21: Data Collection | B21: B2B or B2C Sample through Online Panel Partners with up to 3 quotas on completes | C21: B2B or B2C Sample through Online Panel Partners with up to 3 quotas on completes | D21: B2B or B2C Sample through Online Panel Partners with up to 3 quotas on completes | E21: B2B or B2C Sample through Online Panel Partners with up to 3 quotas on completes | F21: B2B or B2C Sample through Online Panel Partners with up to 3 quotas on completes
B23: CPI * 2.5 / complete | C23: CPI * 2.5 / complete | D23: CPI * 2.5 / complete | E23: CPI * 2.5 / complete | F23: CPI * 2.5 / complete
A25: Analysis & Reporting | B25: Pre Built reports | C25: Reporting - Standard | D25: Reporting - Standard | E25: Reporting - Standard Plus
C26: Data Scrub - Standard | D26: Data Scrub - Standard | E26: Data Scrub - Standard
C27: Crosstabs - Standard | D27: Crosstabs - Standard | E27: Crosstabs - Standard
C28: No Dashboard | D28: No Dashboard | E28: No Dashboard
C29: No Typing Tool | D29: No Typing Tool | E29: No Typing Tool
C30: Open-Ended coding - Standard Plus for 1 OE per Person | D30: Open-Ended coding - Standard Plus for 3 OE per Person | E30: Open-Ended coding Standard Plus for 3 OE per Person
C31: No Weighting | D31: No Weighting | E31: No Weighting
B32: Creative Testing: Additional Fee Require License: Research Core 5
B34: Ad Creative Testing: Included in License Require License: Research Core 3 | C34: $13,000 + $0.68 * n (for OE coding) | D34: $13,000 + $0.68 * 3n (for OE coding) | E34: $18,000 + $0.68 * n (for OE coding) | F34: Custom
A36: Total Base Costs | B36: - | C36: $24,500 + n*(CPI*2.5+$0.68) | D36: $27,000 + n*(CPI*2.5+$2.04) | E36: $32,900 + n*(CPI*2.5+$2.04) | F36: Custom
B38: Optional Add-Ons
B39: Item | C39: Description | D39: Added Costs
B40: Translations - Standard Plus
B41: Translations - Advanced
B42: Data Collection - Standard Plus | D42: Add $1 / Complete
B43: Data Collection - Advanced | D43: Add $2 / Complete
B44: Open-Ended Coding - Standard Plus
B45: Back-End Translations - Standard Plus
B46: Back-End Translations - Advanced
B47: Data Weighting - Standard
B48: Data Weighting - Standard Plus
B49: Data Weighting - Advanced
B50: Typing Tool Programming - Standard | D50: 3000
B51: Typing Tool Programming - Standard Plus | D51: 5000
B52: VoxPopMe
B53: Dialsmith
B54: Eye Square

Sheet Concept Testing
A3: Concept Testing | B3: Concept Testing One- Pager | C3: The investigation of potential consumers reactions to a proposed product or service before introducing it to market. As businesses look to launch a product, concept testing is a valuable step to identify perceptions, wants, and needs associated with a product or service. | G3: Return to Home
B6: XM Solution | C6: Tier 1 - Standard | D6: Tier 2 - Standard Plus | E6: Tier 3 - Advanced | F6: Tier 4 - Custom
A7: Overview | B7: =HYPERLINK("https://www.qualtrics.com/marketplace/concept-testing-study/","https://www.qualtrics.com/marketplace/concept-testing-study/") -> https://www.qualtrics.com/marketplace/concept-testing-study/ | C7: Concept Testing with Basic Reporting on a Smaller Set of Concepts | D7: Concept Testing for a Larger Number of Concepts | E7: Concept Testing with Additional Reporting | F7: Concept Testing with Custom Build Needs, Additional Analytics or Added Deliverables
A9: Design and Build | B9: An expert-built template preloaded with the right questions | C9: Survey Design & Build - Standard Plus | D9: Survey Design & Build - Advanced | E9: Survey Design & Build - Advanced
B10: Ph.D. designed methodology | C10: Sequential or Monadic Design | D10: Sequential or Monadic Design | E10: Sequential or Monadic Design
B11: Prebuilt logic and survey structure | C11: Up to 4 Concepts | D11: Up to 8 Concepts | E11: Up to 8 Concepts
B12: Automated workflow | C12: No translation | D12: No translation | E12: No translation
C13: No typing tool programmed | D13: No typing tool programmed | E13: No typing tool programmed
C14: Optional use of heatmap, hotspot, or highlighter tools | D14: Optional use of heatmap, hotspot, or highlighter tools | E14: Optional use of heatmap, hotspot, or highlighter tools
B18: Included with License Require License: Research Core 3 | C18: 11500 | D18: 14000 | E18: 14000 | F18: Custom
A20: Data Collection | B20: B2B or B2C Sample through Online Panel Partners with up to 3 quotas on completes | C20: B2B or B2C Sample through Online Panel Partners with up to 3 quotas on completes | D20: B2B or B2C Sample through Online Panel Partners with up to 3 quotas on completes | E20: B2B or B2C Sample through Online Panel Partners with up to 3 quotas on completes | F20: B2B or B2C Sample through Online Panel Partners with up to 3 quotas on completes
B22: CPI * 2.5 / complete | C22: CPI * 2.5 / complete | D22: CPI * 2.5 / complete | E22: CPI * 2.5 / complete | F22: CPI * 2.5 / complete
A24: Analysis & Reporting | B24: Pre Built reports | C24: Reporting - Standard | D24: Reporting - Standard | E24: Reporting - Standard Plus
C25: Data Scrub - Standard | D25: Data Scrub - Standard | E25: Data Scrub - Standard
C26: Crosstabs - Standard | D26: Crosstabs - Standard | E26: Crosstabs - Standard
C27: No Dashboard | D27: No Dashboard | E27: No Dashboard
C28: No Typing Tool | D28: No Typing Tool | E28: No Typing Tool
C29: Open-Ended coding - Standard Plus for 1 OE per Person | D29: Open-Ended coding - Standard Plus for 3 OE per Person | E29: Open-Ended coding Standard Plus for 3 OE per Person
C30: No Weighting | D30: No Weighting | E30: No Weighting
B33: Included with License Require License: Research Core 3 | C33: $13,000 + $0.68 * n (for OE coding) | D33: $13,000 + $0.68 * 3n (for OE coding) | E33: $18,000 + $0.68 * n (for OE coding) | F33: 25000
A35: Total Base Costs | B35: - | C35: $24,500 + n*(CPI*2.5+$0.68) | D35: $27,000 + n*(CPI*2.5+$2.04) | E35: $32,900 + n*(CPI*2.5+$2.04) | F35: Custom
B37: Optional Add-Ons
B38: Item | C38: Description | D38: Added Costs
B39: Translations - Standard Plus
B40: Translations - Advanced
B41: Data Collection - Standard Plus | D41: Add $1 / Complete
B42: Data Collection - Advanced | D42: Add $2 / Complete
B43: Open-Ended Coding - Standard Plus
B44: Back-End Translations - Standard Plus
B45: Back-End Translations - Advanced
B46: Data Weighting - Standard
B47: Data Weighting - Standard Plus
B48: Data Weighting - Advanced
B49: Typing Tool Programming - Standard | D49: 3000
B50: Typing Tool Programming - Standard Plus | D50: 5000
B51: VoxPopMe
B52: Crosstabs - Standard Plus

Sheet Competitive Benchmarking
A3: Competitive Benchmarking | C3: Understanding customer satisfation, touchpoints, and interactions with a brand to allow comparison across all brands in the category. | G3: Return to Home
B6: XM Solution | C6: Tier 1 - Standard | D6: Tier 2 - Standard Plus | E6: Tier 3 - Advanced | F6: Tier 4 - Custom
A7: Overview | B7: N/A | C7: Moderate set of competitive brands with high level satisfaction metrics | D7: Moderate set of competitive brands with a deeper dive into products or touchpoint satisfaction | E7: Larger set of competitive brands with a deeper dive into products or touchpoint satisfaction. Includes dashboard.
A9: Design and Build | C9: Survey Design & Build - Standard Plus | D9: Survey Design & Build - Standard Plus | E9: Survey Design & Build - Advanced
C10: Up to 8 brands | D10: Up to 8 brands | E10: Up to 15 brands
C11: Up to 10 touchpoints/product types | D11: Up to 20 touchpoints/product types | E11: Up to 20 touchpoints/product types
C12: No translation | D12: No translation | E12: No translation
C13: No typing tool programmed | D13: No typing tool programmed | E13: No typing tool programmed
B18: - | C18: 11500 | D18: 11500 | E18: 14000 | F18: Custom
A20: Data Collection | C20: B2B or B2C Sample through Online Panel Partners with up to 5 quotas on completes OR nested quotas (2 variables) | D20: B2B or B2C Sample through Online Panel Partners with up to 5 quotas on completes OR nested quotas (2 variables) | E20: B2B or B2C Sample through Online Panel Partners with up to 5 quotas on completes OR nested quotas (2 variables) | F20: B2B or B2C Sample through Online Panel Partners with up to 5 quotas on completes OR nested quotas (2 variables)
B22: - | C22: (CPI * 2.5 + $1) / complete | D22: (CPI * 2.5 + $1) / complete | E22: (CPI * 2.5 + $1) / complete | F22: (CPI * 2.5 + $1) / complete
A24: Analysis & Reporting | C24: Reporting - Standard Plus | D24: Reporting - Advanced | E24: Reporting - Advanced
C25: Data Scrub - Standard | D25: Data Scrub - Standard | E25: Data Scrub - Standard
C26: Crosstabs - Standard | D26: Crosstabs - Standard Plus | E26: Crosstabs - Standard Plus
C27: No Dashboard | D27: No Dashboard | E27: Dashboard - Standard Plus
C28: No Typing Tool | D28: No Typing Tool | E28: No Typing Tool
C29: Open-Ended coding - Standard Plus for 1 OE per Person | D29: Open-Ended coding - Standard Plus for 3 OE per Person | E29: Open-Ended coding Standard Plus for 3 OE per Person
C30: No Weighting | D30: No Weighting | E30: No Weighting
C31: Optional Regression Analysis (1) | D31: Optional Regression Analysis (1) | E31: Optional Regression Analysis (1)
B33: - | C33: $20,500 + $0.68 * n (for OE coding) | D33: $24,500 + $2.04 * n (for OE coding) | E33: $34,500 + $2.04 * n (for OE coding) | F33: Custom
A35: Total Base Costs | B35: - | C35: $32,000 + n*(CPI*2.5+$1.68) | D35: $36,000 + n*(CPI*2.5+$3.04) | E35: $48,500 + n*(CPI*2.5+$3.04) | F35: Custom
B37: Optional Add-Ons
B38: Item | C38: Description | D38: Added Costs
B39: Regression Analysis | D39: 3000
B40: Translations - Standard Plus
B41: Translations - Advanced
B42: Data Collection - Standard Plus | D42: Add $1 / Complete
B43: Data Collection - Advanced | D43: Add $2 / Complete
B44: Open-Ended Coding - Standard Plus
B46: Dashboard - Advanced
B47: Back-End Translations - Standard Plus
B48: Back-End Translations - Advanced
B49: Data Appends - Advanced
B50: Data Appends - Extra Advanced
B51: Data Weighting - Standard
B52: Data Weighting - Standard Plus
B53: Data Weighting - Advanced

Sheet Competitive Landscape  Market L
A3: Competitive Landscape / Market Landscape | C3: Description | G3: Return to Home
B6: XM Solution | C6: Tier 1 - Standard | D6: Tier 2 - Standard Plus | E6: Tier 3 - Advanced | F6: Tier 4 - Custom
A7: Overview | B7: N/A | C7: Smaller | D7: Added imagery and reporting | E7: More brands, imagery, more reporting, regression analysis
A9: Design and Build | C9: Survey Design & Build - Standard | D9: Survey Design & Build - Standard Plus | E9: Survey Design & Build - Advanced
C10: Up to 8 brands | D10: Up to 8 brands | E10: Up to 15 brands
C11: Up to 10 imagery statements | D11: Up to 20 imagery statements | E11: Up to 20 imagery statements
C12: No translation | D12: No translation | E12: No translation
C13: No typing tool programmed | D13: No typing tool programmed | E13: No typing tool programmed
B18: - | C18: 8000 | D18: 11500 | E18: 14000 | F18: Custom
A20: Data Collection | C20: B2B or B2C Sample through Online Panel Partners with up to 3 quotas on completes | D20: B2B or B2C Sample through Online Panel Partners with up to 3 quotas on completes | E20: B2B or B2C Sample through Online Panel Partners with up to 3 quotas on completes | F20: B2B or B2C Sample through Online Panel Partners with up to 3 quotas on completes
B22: - | C22: CPI * 2.5 / complete | D22: CPI * 2.5 / complete | E22: CPI * 2.5 / complete | F22: CPI * 2.5 / complete
A24: Analysis & Reporting | C24: Reporting - Standard | D24: Reporting - Standard Plus | E24: Reporting - Advanced
C25: Data Scrub - Standard | D25: Data Scrub - Standard | E25: Data Scrub - Standard
C26: Crosstabs - Standard | D26: Crosstabs - Standard | E26: Crosstabs - Standard
C27: No Dashboard | D27: No Dashboard | E27: No Dashboard
C28: No Typing Tool | D28: No Typing Tool | E28: No Typing Tool
C29: Open-Ended coding - Standard Plus, for 1 OE per Person | D29: Open-Ended coding - Standard Plus, for 1 OE per Person | E29: Open-Ended coding - Standard Plus, for 1 OE per Person
C30: No Weighting | D30: No Weighting | E30: No Weighting
C31: No Regression Analysis | D31: No Regression Analysis | E31: Optional Regression Analysis (1)
C32: No market sizing analysis | D32: No market sizing analysis | E32: No market sizing analysis
B33: - | C33: $13,000 + $0.68 * n (for OE coding) | D33: $18,000 + $0.68 * n (for OE coding) | E33: $24,500 + $0.68 * n (for OE coding)
A35: Total Base Costs | B35: - | C35: $21,000 + n*(CPI*2.5+$0.68) | D35: $29,500 + n*(CPI*2.5+$0.68) | E35: $37,500 + n*(CPI*2.5+$0.68) | F35: Custom
B37: Optional Add-Ons
B38: Item | C38: Description | D38: Added Costs
B39: Regression Analysis | D39: 3000
B40: Translations - Standard Plus
B41: Translations - Advanced
B42: Data Collection - Standard Plus | D42: Add $1 / Complete
B43: Data Collection - Advanced | D43: Add $2 / Complete
B44: Open-Ended Coding - Standard Plus
B45: Factor Analysis
B46: Dashboard - Advanced
B47: Back-End Translations - Standard Plus
B48: Back-End Translations - Advanced
B49: Data Appends - Advanced
B50: Data Appends - Extra Advanced
B51: Data Weighting - Standard
B52: Data Weighting - Standard Plus
B53: Data Weighting - Advanced

Sheet Message Testing w MaxDiff
A3: Message Testing w/ MaxDiff | B3: Link to One- Pager | C3: With a MaxDiff methodology, we can test 10 to 25 potential messages and determine the optimal set messages to include in communications or across an advertisement campaign and maximize ROI during communication development and launch. | G3: Return to Home
A4: Note, pricing below is for full-service (end-to-end) only and includes a full survey build and PPT report in additional to the MaxDiff. Please see the "Ad-Hoc | Reporting & Analytics" tab for MaxDiff costs without other services.
B6: XM Solution | C6: Tier 1 - Standard | D6: Tier 2 - Standard Plus | E6: Tier 3 - Advanced | F6: Tier 4 - Custom
A7: Overview | B7: N/A | C7: MaxDiff with 8-20 statements and Standard Reportng | D7: MaxDiff with 8-20 statements and Reporting and TURF Analysis & Simulator | E7: MaxDiff with 8-20 statements with additional Analysis including Message Refinement, TURF Analysis & Simulator
A9: Design and Build | C9: Survey Design & Build - Standard | D9: Survey Design & Build - Standard | E9: Survey Design & Build - Standard Plus
C10: MaxDiff Design & Analysis - Standard | D10: MaxDiff Design & Analysis - Standard | E10: MaxDiff Design & Analysis - Standard Plus
C11: No Translation | D11: No Translation | E11: No Translation
C12: No typing tool programmed | D12: No typing tool programmed | E12: No typing tool programmed
E13: Message refinement via heatmap, hotspot, or highlighter tools
B18: - | C18: 13000 | D18: 13000 | E18: 19000 | F18: Custom
A20: Data Collection | C20: B2B or B2C Sample through Online Panel Partners with up to 3 quotas on completes | D20: B2B or B2C Sample through Online Panel Partners with up to 3 quotas on completes | E20: B2B or B2C Sample through Online Panel Partners with up to 3 quotas on completes | F20: B2B or B2C Sample through Online Panel Partners with up to 3 quotas on completes
B22: - | C22: CPI * 2.5 / complete | D22: CPI * 2.5 / complete | E22: CPI * 2.5 / complete | F22: CPI * 2.5 / complete
A24: Analysis & Reporting | C24: Reporting - Standard | D24: Reporting - Standard | E24: Reporting - Standard Plus
C25: Data Scrub - Standard | D25: Data Scrub - Standard | E25: Data Scrub - Standard
C26: Crosstabs - Standard | D26: Crosstabs - Standard | E26: Crosstabs - Standard
C27: MaxDiff Design & Analysis - Standard | D27: MaxDiff Design & Analysis - Standard | E27: MaxDiff Design & Analysis - Standard Plus
C28: No TURF Analysis | D28: TURF Analysis & Simulator | E28: TURF Analysis & Simulator
C29: No Dashboard | D29: No Dashboard | E29: No Dashboard
C30: No Typing Tool | D30: No Typing Tool | E30: No Typing Tool
C31: No Open-Ended coding | D31: No Open-Ended coding | E31: No Open-Ended coding
C32: No Weighting | D32: No Weighting | E32: No Weighting
B33: - | C33: 13000 | D33: 16000 | E33: 21000 | F33: Custom
A35: Total Base Costs | B35: - | C35: $26,000 + n*(CPI*2.5) | D35: $29,000 + n*(CPI*2.5) | E35: $40,000 + n*(CPI*2.5) | F35: Custom
B37: Optional Add-Ons
B38: Item | C38: Description | D38: Added Costs
B39: Translations - Standard Plus
B40: Translations - Advanced
B41: Data Collection - Standard Plus | D41: Add $1 / Complete
B42: Data Collection - Advanced | D42: Add $2 / Complete
B43: Open-Ended Coding - Standard Plus
B44: Back-End Translations - Standard Plus
B45: Back-End Translations - Advanced
B46: Data Weighting - Standard
B47: Data Weighting - Standard Plus
B48: Data Weighting - Advanced
B49: VoxPopMe

Sheet Product Development w Conjoint
A3: Product Development w/ Conjoint | B3: Link to One- Pager | C3: Conjoint analysis is an advanced analytic technique which assesses the importance consumers place on different features of a given product or service. | G3: Return to Home
A4: Note, pricing below is for full-service (end-to-end) only and includes a full survey build and PPT report in additional to the Conjoint. Please see the "Ad-Hoc | Reporting & Analytics" tab for Conjoint costs without other services.
B6: Conjoint Tool | C6: Tier 1 - Standard | D6: Tier 2 - Standard Plus | E6: Tier 3 - Advanced | F6: Tier 4 - Custom
A7: Overview | B7: =HYPERLINK("https://www.qualtrics.com/marketplace/conjoint-package-analysis/","https://www.qualtrics.com/marketplace/conjoint-package-analysis/") -> https://www.qualtrics.com/marketplace/conjoint-package-analysis/ | C7: Conjoint with 3-7 Features, each with 2-5 levels, a standard survey build around the conjoint, and basic reporting | D7: Conjoint with 3-7 Features, each with 2-5 levels, a more complex survey build around the conjoint and additional reporting | E7: More advanced conjoint with survey build and additional reporting
A9: Design and Build | B9: An expert-built template preloaded with the right questions | C9: Survey Design & Build - Standard | D9: Survey Design & Build - Standard Plus | E9: Survey Design & Build - Standard Plus
B10: Ph.D. designed methodology | C10: Conjoint Design & Analysis - Standard Plus | D10: Conjoint Design & Analysis - Standard Plus | E10: Conjoint Design & Analysis - Advanced
B11: Prebuilt logic and survey structure | C11: No Translation | D11: No Translation | E11: No Translation
B12: Automated workflow | C12: No typing tool programmed | D12: No typing tool programmed | E12: No typing tool programmed
B18: Additional Fee Required License: Research Core 3 | C18: 20000 | D18: 23500 | E18: 25500 | F18: Custom
A20: Data Collection | B20: B2B or B2C Sample through Online Panel Partners with up to 3 quotas on completes | C20: B2B or B2C Sample through Online Panel Partners with up to 3 quotas on completes | D20: B2B or B2C Sample through Online Panel Partners with up to 3 quotas on completes | E20: B2B or B2C Sample through Online Panel Partners with up to 3 quotas on completes | F20: B2B or B2C Sample through Online Panel Partners with up to 3 quotas on completes
B22: CPI * 2.5 / complete | C22: CPI * 2.5 / complete | D22: CPI * 2.5 / complete | E22: CPI * 2.5 / complete | F22: CPI * 2.5 / complete
A24: Analysis & Reporting | B24: Pre Built reports | C24: Reporting - Standard | D24: Reporting - Standard Plus | E24: Reporting - Standard Plus
C25: Data Scrub - Standard | D25: Data Scrub - Standard | E25: Data Scrub - Standard
C26: Crosstabs - Standard | D26: Crosstabs - Standard | E26: Crosstabs - Standard
C27: Conjoint Design & Analysis - Standard Plus | D27: Conjoint Design & Analysis - Standard Plus | E27: Conjoint Design & Analysis - Advanced
C28: No TURF Analysis | D28: No TURF Analysis | E28: No TURF Analysis
C29: No Dashboard | D29: No Dashboard | E29: No Dashboard
C30: No Typing Tool | D30: No Typing Tool | E30: No Typing Tool
C31: No Open-Ended coding | D31: No Open-Ended coding | E31: No Open-Ended coding
C32: No Weighting | D32: No Weighting | E32: No Weighting
B33: Additional Fee Required License: Research Core 3 | C33: 13000 | D33: 18000 | E33: 18000 | F33: Custom
A35: Total Base Costs | B35: - | C35: $33,000 + n*(CPI*2.5) | D35: $41,500 + n*(CPI*2.5) | E35: $43,500 + n*(CPI*2.5) | F35: Custom
B37: Optional Add-Ons
B38: Item | C38: Description | D38: Added Costs
B39: Translations - Standard Plus
B40: Translations - Advanced
B41: Data Collection - Standard Plus | D41: Add $1 / Complete
B42: Data Collection - Advanced | D42: Add $2 / Complete
B43: Open-Ended Coding - Standard Plus
B44: Back-End Translations - Standard Plus
B45: Back-End Translations - Advanced
B46: Data Weighting - Standard
B47: Data Weighting - Standard Plus
B48: Data Weighting - Advanced
B49: VoxPopMe
B50: TURF Analysis - Standard | D50: 2000
B51: TURF Analysis - Standard Plus | D51: 3000

Sheet Segmentation
A3: Segmentation | B3: =HYPERLINK("https://drive.google.com/file/d/1KLIqnSiRhfUMIG3X_P4wHpXKxQI0ZEac/view?usp=sharing","Segmentation One- Pager") -> Segmentation One- Pager | C3: Breaking up the overall market into clearly identifiable segments having similar wants and needs characteristics. A subset are often then selected as "target segments" based on their economic potential, as well as, receptivity to the brand. | G3: Return to Home
B6: XM Solution | C6: Tier 1 - Standard | D6: Tier 2 - Standard Plus | E6: Tier 3 - Advanced | F6: Tier 4 - Custom
A7: Overview | B7: N/A | C7: Standard Full-Service Segmentation with Reporting, CrossTabs and Typing Tool for Future Research | F7: Custom Segmentation Design and/or Analysis
A9: Design and Build | C9: Survey Design & Build - Advanced | F9: Tier 1, plus custom design needs
C10: No translations
B18: - | C18: 14000 | F18: Custom Quote
A20: Data Collection | C20: B2B or B2C Sample through Online Panel Partners with up to 3 quotas on completes | F20: B2B or B2C Sample through Online Panel Partners with up to 3 quotas on completes
B22: - | C22: CPI * 2.5 / complete | F22: CPI * 2.5 / complete
A24: Analysis & Reporting | C24: Reporting - Advanced | F24: Tier 1, plus custom analytic needs
C25: Data Scrub - Standard
C26: Crosstabs - Standard Plus
C27: Segmentation (Clustering Analysis)
C28: Importing of the Segment Variable
C29: No Dashboard
C30: Typing Tool
C31: No Open-Ended coding
C32: No Weighting
B33: - | C33: 43750 | F33: Custom Quote
A35: Total Base Costs | B35: - | C35: $57,750 + n*(CPI*2.5) | F35: Custom
B37: Optional Add-Ons
B38: Item | C38: Description | D38: Added Costs
B39: Market Sizing Analysis | D39: 2000
B40: Translations - Standard Plus
B41: Translations - Advanced
B42: Data Collection - Standard Plus | D42: Add $1 / Complete
B43: Data Collection - Advanced | D43: Add $2 / Complete
B44: Open-Ended Coding - Standard Plus | D44: $0.68 per complete
B45: Dashboard - Standard Plus
B46: Dashboard - Advanced
B47: Back-End Translations - Standard Plus
B48: Back-End Translations - Advanced
B49: Data Appends - Advanced
B50: Data Appends - Extra Advanced
B51: Data Weighting - Standard
B52: Data Weighting - Standard Plus
B53: Data Weighting - Advanced

Sheet Product Development w MaxDiff
A3: Product Development w/ MaxDiff | C3: With a MaxDiff methodology, we can test 10 to 25 potential product features and determine the optimal set features to include in product(s) to maximize consumer interest, volume, and revenue. | G3: Return to Home
A4: Note, pricing below is for full-service (end-to-end) only and includes a full survey build and PPT report in additional to the MaxDiff. Please see the "Ad-Hoc | Reporting & Analytics" tab for MaxDiff costs without other services.
B6: XM Solution | C6: Tier 1 - Standard | D6: Tier 2 - Standard Plus | E6: Tier 3 - Advanced | F6: Tier 4 - Custom
A7: Overview | B7: https://www.qualtrics.com/marketplace/max-diff-software-tool/ | C7: MaxDiff with 8-20 Product Features and Standard Reportng | D7: MaxDiff with 8-20 Product Features and Reporting and TURF Analysis & Simulator | E7: MaxDiff with 8-20 Product Features with additional Analysis including Feature Refinement, TURF Analysis & Simulator
A9: Design and Build | B9: An expert-built template preloaded with the right questions | C9: Survey Design & Build - Standard | D9: Survey Design & Build - Standard | E9: Survey Design & Build - Standard Plus
B10: Ph.D. designed methodology | C10: MaxDiff Design & Analysis - Standard Plus | D10: MaxDiff Design & Analysis - Standard Plus | E10: MaxDiff Design & Analysis - Standard Plus
B11: Prebuilt logic and survey structure | C11: No Translation | D11: No Translation | E11: No Translation
B12: Automated workflow | C12: No typing tool programmed | D12: No typing tool programmed | E12: No typing tool programmed
E13: Message refinement via heatmap, hotspot, or highlighter tools
B18: Additional Fee Required License: Research Core 3 | C18: 13000 | D18: 13000 | E18: 19000 | F18: Custom
A20: Data Collection | B20: B2B or B2C Sample through Online Panel Partners with up to 3 quotas on completes | C20: B2B or B2C Sample through Online Panel Partners with up to 3 quotas on completes | D20: B2B or B2C Sample through Online Panel Partners with up to 3 quotas on completes | E20: B2B or B2C Sample through Online Panel Partners with up to 3 quotas on completes | F20: B2B or B2C Sample through Online Panel Partners with up to 3 quotas on completes
B22: CPI * 2.5 / complete | C22: CPI * 2.5 / complete | D22: CPI * 2.5 / complete | E22: CPI * 2.5 / complete | F22: CPI * 2.5 / complete
A24: Analysis & Reporting | B24: Pre Built reports | C24: Reporting - Standard | D24: Reporting - Standard | E24: Reporting - Standard Plus
C25: Data Scrub - Standard | D25: Data Scrub - Standard | E25: Data Scrub - Standard
C26: Crosstabs - Standard | D26: Crosstabs - Standard | E26: Crosstabs - Standard
C27: MaxDiff Design & Analysis - Standard | D27: MaxDiff Design & Analysis - Standard | E27: MaxDiff Design & Analysis - Standard Plus
C28: No TURF Analysis | D28: TURF Analysis & Simulator | E28: TURF Analysis & Simulator
C29: No Dashboard | D29: No Dashboard | E29: No Dashboard
C30: No Typing Tool | D30: No Typing Tool | E30: No Typing Tool
C31: No Open-Ended coding | D31: No Open-Ended coding | E31: No Open-Ended coding
C32: No Weighting | D32: No Weighting | E32: No Weighting
B33: Additional Fee Required License: Research Core 3 | C33: 13000 | D33: 16000 | E33: 21000 | F33: Custom
A35: Total Base Costs | B35: - | C35: $26,000 + n*(CPI*2.5) | D35: $29,000 + n*(CPI*2.5) | E35: $40,000 + n*(CPI*2.5) | F35: Custom
B37: Optional Add-Ons
B38: Item | C38: Description | D38: Added Costs
B39: Translations - Standard Plus
B40: Translations - Advanced
B41: Data Collection - Standard Plus | D41: Add $1 / Complete
B42: Data Collection - Advanced | D42: Add $2 / Complete
B43: Open-Ended Coding - Standard Plus
B44: Back-End Translations - Standard Plus
B45: Back-End Translations - Advanced
B46: Data Weighting - Standard
B47: Data Weighting - Standard Plus
B48: Data Weighting - Advanced
B49: VoxPopMe

Sheet BX | Implementation & Services
A3: BX - Brand Tracking | B3: =HYPERLINK("https://success.qualtrics.com/rs/542-FMF-412/images/Brand%20Tracking%20Graphic.pdf","Qualtrics BX Infographic") -> Qualtrics BX Infographic | C3: Understand your market, your brand performance, and your competitors better than ever before. Qualtrics BrandXM™ gives you easy-to-use tools to help you: Strengthen brand equity Improve brand perceptions And drive sustainable growth | G3: Return to Home
B6: XM Solution | C6: Tier 1 - Standard | D6: Tier 2 - Standard Plus | E6: Tier 3 - NA | F6: Tier 4 - Custom
A7: Overview
A9: Design & Build
A10: Implementation | B10: N/A | F10: Custom quote required if: Multiple dashboards or builds Over 60 questions Multiple pathways or links Over 20 dashboard filters Large number of custom metrics Multiple data sources Other items not covered in Standard or Standard Plus
F11: Custom Quote
A14: Data Migration - Internal | B14: N/A | C14: Includes migrating 1 survey and 1 dashboard from CoreXM or CX to BX. Assumptions: Other than enabling these existing projects to have access to BX technology, no other survey or dashboard edits are included. Modifications outside of this migration require additional scoping and costs.
C15: 3000
A18: Data Migration - External | B18: N/A | C18: Includes migration from an external data source (CRM, sales data, etc.)
C19: Custom
A22: Survey Review & Consultation | B22: N/A | C22: Includes methodology review and consultation for: 1 survey in English Up to 30 questions 1 survey pathway (no differences by market/category) Up to 20 brands (including competitors) Up to 2 rounds of iteration (one round of customer marked-up feedback on question content, response options, or logic that impacts 5 or more questions) Assumptions: The customer provides a fully written out questionnaire, including demographics and screener questions. Bullets or partially written questions will require design services and an additional cost. The customer provides the questionnaire in a Word file, Google Doc, or similar format. Excel or Google Sheet formats will require additional scoping and costs. | D22: Includes methodology review and consultation for: 1 survey in English Up to 60 questions 1 survey pathway (no differences by market/category) Up to 20 brands (including competitors) Up to 3 rounds of iteration (one round of customer marked-up feedback on question content, response options, or logic that impacts 5 or more questions) Assumptions: The customer provides a fully written out questionnaire, including demographics and screener questions. Bullets or partially written questions will require design services and an additional cost. The customer provides the questionnaire in a Word file, Google Doc, or similar format. Excel or Google Sheet formats will require additional scoping and costs. | F22: Includes methodology review and consultation for: Multiple surveys Surveys over 60 questions Surveys with multiple pathways Other cases not covered in standard or standard plus
C23: 3000 | D23: 4500 | F23: Custom Quote
A26: Survey Design | B26: N/A | C26: Includes design for: 1 survey in English Up to 30 questions 1 survey pathway (no differences by market/category) Up to 20 brands (including competitors) Up to 10 brand attributes/imagery statements Up to 2 rounds of iteration (one round of customer marked-up feedback on question content, response options, or logic that impacts 5 or more questions) Includes design consultation on dashboard layout and content Estimated Timing: 1-2 weeks | D26: Includes design for: 1 survey in English Up to 60 questions 1 survey pathway (no differences by market/category) Up to 20 brands (including competitors) Up to 20 brand attributes/imagery statements Up to 3 rounds of iteration (one round of customer marked-up feedback on question content, response options, or logic that impacts 5 or more questions) Includes design consultation on dashboard layout and content Estimated Timing: 1-2 weeks | F26: Includes survey design for: Multiple surveys Surveys over 60 questions Surveys with multiple pathways Other cases not covered in standard or standard plus
C27: 6000 | D27: 8000 | F27: Custom Quote
A30: Consultation Services - Research Experts | B30: N/A | C30: Research Analyst or Specialist Customer may engage a Qualtrics research expert for survey programming, dashboard programming, analytics support, data consultation and data interpretation. | D30: Research Manager Customer may engage a Qualtrics research manager for analytics support, data consultation and data interpretation.
C31: $250 per hour | D31: $350 per hour
A33: Consultation Services - XM Scientists | B33: N/A | C33: Customer may engage a Qualtrics XMS for methodology or analytics advice and consultation.
C34: $350 per hour
A36: Consultation Services - Tech Consultant | B36: N/A | C36: Customer may engage a Qualtrics technology consultation for survey programming and dashboard programming.
C37: $250 per hour
A39: BX Ongoing Success Packages: Base | B39: N/A | C39: Support on BX Licenses which includes: Standard Product Support & Customer Success
A40: Customer Profile: Stable program, declines support and willing to be self-sufficient; typically <$60k in spend | C40: Included with all BX licenses (CSM coverage varies by spend tier and included only if license spend >$50k) | F40: Custom Quote
A42: BX Ongoing Success Packages: Guided | B42: N/A | C42: Support on BX Licenses which includes: Standard Product Support & Customer Success Quarterly consulting retainer for up to 5 hours per quarter that could be used for: Minor question or dashboard edits Data interpretation and consulting Thought partnership | D42: Support on BX Licenses which includes: Standard Product Support & Customer Success Quarterly consulting retainer for up to 10 hours per quarter that could be used for: Minor question or dashboard edits Data interpretation and consulting Thought partnership | E42: Support on BX Licenses which includes: Standard Product Support & Customer Success Quarterly consulting retainer for up to 15 hours per quarter that could be used for: Minor question or dashboard edits Data interpretation and consulting Thought partnership
A43: Customer Profile: Moderate complexity programs, likely to require light updates and assistance | C43: $6,000/year | D43: $12,000/year | E43: $18,000/year | F43: Custom Quote
A45: BX Ongoing Success Packages: Advanced | B45: N/A | C45: Support on BX Licenses which includes: Standard Product Support & Customer Success Quarterly consulting retainer for up to 10 hours per quarter that could be used for: Minor question or dashboard edits Data intepretation and consulting Thought partnership Technical Account Manager, to provide higher level of program-specific platform support and configuration updates, for up to 5 hours per week
A46: Customer Profile: Highly complex enterprise programs with need for ongoing designated platform support | C46: $62,000/year ($50,000 for TAM, $12,000 for Consulting) | F46: Custom Quote

Sheet Core XM | Implementation & Serv
A3: Core XM Implementation and Services | B3: CoreXM Delivery Package Detail | G3: Return to Home
B6: Self-Service | C6: Tier 1 - Standard | D6: Tier 2 - Standard Plus | E6: Tier 3 - Advanced | F6: Tier 4 - Custom
A7: Overview
A9: Design & Build
A10: CoreXM Implementation | B10: Small to midsize orgs using internal resources with Business Edition $0-100K ARR, no add-ons | C10: Standard Delivery Package Implementation designed for midsize orgs using in house resources. Business Edition ($50k-$100k) License Tier. Includes: Project Management Kickoff call Pre-launch review Up to 8 hours of designated project consultant Estimated timeline: 4 weeks | D10: Standard Plus Delivery Package Implementation designed for larger programs, 1-2 use cases, growing internal capabilities Business Edition (up to $100k) License Tier. Includes: Project Management Kickoff call Pre-launch review Detailed project plan Up to 16 hours of designated project consultant Estimated timeline: 8 weeks | E10: Enterprise Essentials Delivery Package Implementation designed for Complex XM programs Multiple use cases. Involves consultation and implementation Business Edition (over $100k) License Tier. Enterprise Edition Under $1M ARR Includes: Project Management Kickoff call Pre-launch review Detailed project plan Up to TBD hours of designated project consultant Estimated timeline: TBD weeks | F10: Enterprise Premier Delivery Package Implementation designed for Complex XM programs with Multiple use cases that Require high-touch. Involves Premium consultation and implementation Enterprise Edition Over $1M ARR Includes: Project Management Kickoff call Pre-launch review Detailed project plan Up to TBD hours of designated project consultant Estimated timeline: TBD weeks
C11: 2000 | D11: 4000 | E11: Custom | F11: Custom
A14: Custom XM Solutions | B14: N/A | C14: Creation of a Custom XM Solution which includes Design & Build, Guided Interface Set-Up, and Creation of Report Templates. Specifically, this includes: Up to survey 20 questions Light survey flow logic Design review and consultation No tie in with MaxDiff, Conjoint, or other advanced analytic tools Guided interface 5 pre-built report pages with no custom widgets Up to 2 iterations per deliverable | D14: Creation of a Custom XM Solution which includes Design & Build, Guided Interface Set-Up, and Creation of Report Templates. Specifically, this includes: Up to survey 40 questions Moderate survey flow logic Design review and consultation No tie in with MaxDiff, Conjoint, or other advanced analytic tools Guided interface 10 pre-built report pages with no custom widgets Up to 2 iterations per deliverable | E14: Creation of a Custom XM Solution which includes Design & Build, Guided Interface Set-Up, and Creation of Report Templates. Specifically, this includes: Up to survey 60 questions Complex survey flow logic Design review and consultation No tie in with MaxDiff, Conjoint, or other advanced analytic tools Guided interface 15 pre-built report pages with no custom widgets Up to 3 iterations per deliverable | F14: Creation of a Custom XM Solution which includes Design & Build, Guided Interface Set-Up, and Creation of Report Templates. Custom scope required for surveys over 60 questions, requiring over 15 report pages, requiring custom widgets, involving a dashboard or more advance reporting, etc.
A15: Note: CoreXM5 license required to create | C15: 20000 | D15: 30000 | E15: 35000 | F15: Custom Quote
A18: Solution Configuration Updates (Add-on) | B18: N/A | C18: Updates to the Survey Design & Build, Guided Interface, and Report Templates Deliverables - Up to 20% change in each component performed under the respective Deliverable (Survey Design &amp; Build, Guided Interface, and Report Templates) - All requests must be presented together with each update - Up to 2 iterations for each deliverable, per instance of updates - Provided in English | F18: Updates to the Survey Design & Build, Guided Interface, and Report Templates Deliverables - Up to 20% change in each component performed under the respective Deliverable (Survey Design &amp; Build, Guided Interface, and Report Templates) - All requests must be presented together with each update - Up to 2 iterations for each deliverable, per instance of updates - Provided in English
A19: Note: CoreXM5 license required to edit | C19: Custom Quote | F19: Custom Quote
A22: Additional Dashboard Configuration (price per dashboard) | B22: N/A | C22: Support for Standard Survey: Support client’s build of survey with max 30 Questions, 30 Embedded Data Fields; Standard Dashboard Build: Max 20 widgets/survey, max 60 widgets total, max 3 roles
C23: 2500
A26: Additional Support | B26: N/A | C26: Additional SI Intercept Setup (price per intercept, each on a single domain or app): $500 Additional Site Intercept Support (per domain or app, includes one intercept): $2,500 Additional Survey Support (<30 questions, price per survey): $1,500 Additional Survey Support (30-60 questions, price per survey): $3,000 Developer Tools Advanced Support (Must be sold in conjunction with DeveloperTools Introductory Support): $3,000 XM Directory Automations Support (price per automation): $1,000
C27: $500 - $3000
A30: Batch user creation | B30: N/A | C30: User creation of up to 1000 users
C31: 1000
A34: Translation support | B34: N/A | C34: Dashboard Translation Support (price per dashboard, per language): $1,000 Survey Translation Support (price per survey, per language): $1,000
C35: 1000
A38: Data migration | B38: N/A | C38: Data Migration (per source, up to 50k responses each)
C39: 2000
A42: Custom Training/Demo | B42: N/A | C42: Custom Training/Demo (price per 1-hour session)
C43: 400

Sheet Ad-Hoc | Design and Build
A3: Ad-Hoc | Design and Build | C3: Prepping a survey for data collection by ensuring a sound design and methodology, building in Qualtrics and/or translating into other languages. | G3: Return to Home
B6: XM Solution | C6: Tier 1 - Standard | D6: Tier 2 - Standard Plus | E6: Tier 3 - Advanced | F6: Tier 4 - Custom
A7: Overview
A9: Design & Build
A10: Methodology Review and Consultation | B10: N/A | C10: Qualtrics will review one (1) survey for Customer. Such survey review will include: Up to 30 questions (each individual statement in a matrix or similar format counts as a question) Unless otherwise agreed, such survey review will not include: Technical review or testing Survey build or survey programming edits Delivery Team Responsibilities: If necessary, conduct kick-off call to discuss research objectives. Provide methodological expertise on best design practices and technical expertise on what is feasible in the platform. Conduct Quality Assurance (QA) for Customer's survey design. Share recommendations for Customer review. Customer Responsibilities: Provide a fully written out questionnaire, including demographics and screener questions. Bullets or partially written questions will be subject to additional fees and further scoping by Qualtrics. Provide the questionnaire in a .doc file, Google Doc, or similar format. Spreadsheet formats (.xls, Google Sheets, etc.) will be subject to additional fees and further scoping by Qualtrics. Assumptions: After initial survey recommendations are shared, Customer may request up to 2 rounds of iteration for review (Customer marked-up feedback on question content, response options, or logic that impacts 5 or more questions) Estimated Timing: 3-5 business days | D10: Qualtrics will review one (1) survey for Customer. Such survey review will include: Up to 60 questions (each individual statement in a matrix or similar format counts as a question) Unless otherwise agreed, such survey review will not include: Technical review or testing Survey build or survey programming edits Delivery Team Responsibilities: If necessary, conduct kick-off call to discuss research objectives. Provide methodological expertise on best design practices and technical expertise on what is feasible in the platform. Conduct Quality Assurance (QA) for Customer's survey design. Share recommendations for Customer review. Customer Responsibilities: Provide a fully written out questionnaire, including demographics and screener questions. Bullets or partially written questions will be subject to additional fees and further scoping by Qualtrics. Provide the questionnaire in a .doc file, Google Doc, or similar format. Spreadsheet formats (.xls, Google Sheets, etc.) will be subject to additional fees and further scoping by Qualtrics. Assumptions: After initial survey recommendations are shared, Customer may request up to 3 rounds of iteration for review (Customer marked-up feedback on question content, response options, or logic that impacts 5 or more questions) Estimated Timing: 3-5 business days | E10: Qualtrics will review one (1) survey for Customer. Such survey review will include: Up to 100 questions (each individual statement in a matrix or similar format counts as a question) Unless otherwise agreed, such survey review will not include: Technical review or testing Survey build or survey programming edits Delivery Team Responsibilities: If necessary, conduct kick-off call to discuss research objectives. Provide methodological expertise on best design practices and technical expertise on what is feasible in the platform. Conduct Quality Assurance (QA) for Customer's survey design. Share recommendations for Customer review. Customer Responsibilities: Provide a fully written out questionnaire, including demographics and screener questions. Bullets or partially written questions will be subject to additional fees and further scoping by Qualtrics. Provide the questionnaire in a .doc file, Google Doc, or similar format. Spreadsheet formats (.xls, Google Sheets, etc.) will be subject to additional fees and further scoping by Qualtrics. Assumptions: After initial survey recommendations are shared, Customer may request up to 4 rounds of iteration for review (Customer marked-up feedback on question content, response options, or logic that impacts 5 or more questions) Estimated Timing: 5-7 business days | F10: Custom quote for multiple surveys, review of a translated survey, or advanced consultation needs
C11: 2100 | D11: 3100 | E11: 5100 | F11: Custom Quote
A12: *Bundled with Reporting | C12: 2000 | D12: 3000 | E12: 5000
C13: SRC-01 | D13: SRC-02 | E13: SRC-03 | F13: SRC-04
A15: Survey Design & Build | B15: N/A | C15: Includes design and programming for: 1 survey in English Up to 30 questions or elements (Embedded Data, hidden variables, individual statements in a matrix or similar format) Light survey flow logic (fewer than 10 survey flow elements such as randomizers and branches) Up to 2 rounds of iteration for design (one round of customer marked-up feedback on question content, response options, or logic that impacts 5 or more questions) Assumptions: After the Qualtrics test link is shared, the customer may request up to a total of 2 hours of additional programming changes (new wording, logic, etc.). Changes after this point will require additional scoping and fees. All corrections (programmer errors) will be addressed and do not count toward these programming hours. Only existing platform functionality will be used. Requests that are outside of platform functionality or require custom coding may require additional scoping and cost. The customer is responsible for providing any images or video files required in the correct format, resolution, dimensions, and file size. Qualtrics will not source or modify any files. No manual implementation of customer-provided translations is included. Estimated Timing: ~4 weeks (1 week for design, 1 week for client review, 1 week for programming, 1 week for client review) | D15: Includes design and programming for: 1 survey in English Up to 60 questions or elements (Embedded Data, hidden variables, individual statements in a matrix or similar format) Moderate survey flow logic (fewer than 50 survey flow elements such as randomizers and branches) Up to 3 rounds of iteration for design (one round of customer marked-up feedback on question content, response options, or logic that impacts 5 or more questions) Assumptions: After the Qualtrics test link is shared, the customer may request up to a total of 3 hours of additional programming changes (new wording, logic, etc.). Changes after this point will require additional scoping and fees. All corrections (programmer errors) will be addressed and do not count toward these programming hours. Only existing platform functionality will be used. Requests that are outside of platform functionality or require custom coding may require additional scoping and cost. The customer is responsible for providing any images or video files required in the correct format, resolution, dimensions, and file size. Qualtrics will not source or modify any files. No manual implementation of customer-provided translations is included. Estimated Timing: ~4 weeks (1 week for design, 1 week for client review, 1 week for programming, 1 week for client review) | E15: Includes design and programming for: 1 survey in English Up to 100 questions or elements (Embedded Data, hidden variables, individual statements in a matrix or similar format) Heavy survey flow logic (fewer than 100 survey flow elements such as randomizers and branches) Up to 4 rounds of iteration for design (one round of customer marked-up feedback on question content, response options, or logic that impacts 5 or more questions) Assumptions: After the Qualtrics test link is shared, the customer may request up to a total of 4 hours of additional programming changes (new wording, logic, etc.). Changes after this point will require additional scoping and fees. All corrections (programmer errors) will be addressed and do not count toward these programming hours. Only existing platform functionality will be used. Requests that are outside of platform functionality or require custom coding may require additional scoping and cost. The customer is responsible for providing any images or video files required in the correct format, resolution, dimensions, and file size. Qualtrics will not source or modify any files. No manual implementation of customer-provided translations is included. Estimated Timing: ~5 weeks (1 week for design, 1 week for client review, 2 weeks for programming, 1 week for client review) | F15: Custom quote for survey with over 100 questions or elements, email or other triggers built in, advanced coding (javascript, API calls, HTML, etc.), multiple surveys, advanced analytics (MaxDiff, etc.)
C16: 8000 | D16: 11500 | E16: 14000 | F16: Custom Quote
C17: SDB-01 | D17: SDB-02 | E17: SDB-03 | F17: SDB-04
A19: Survey Design (without Build) | B19: N/A | C19: Includes design for: 1 survey in English Up to 30 questions or elements (Embedded Data, hidden variables, individual statements in a matrix or similar format) Light survey flow logic (fewer than 10 survey flow elements such as randomizers, blocks, and branches) noted in document Up to 2 rounds of iteration (one round of customer marked-up feedback on question content, response options, or logic that impacts 5 or more questions) Estimated Timing: ~2 weeks (1 week for design, 1 week for client review) | D19: Includes design for: 1 survey in English Up to 60 questions or elements (Embedded Data, hidden variables, individual statements in a matrix or similar format) Moderate survey flow logic (fewer than 50 survey flow elements such as randomizers, blocks, and branches) noted in document Up to 3 rounds of iteration (one round of customer marked-up feedback on question content, response options, or logic that impacts 5 or more questions) Estimated Timing: ~2 weeks (1 week for design, 1 week for client review) | E19: Includes design for: 1 survey in English Up to 100 questions or elements (Embedded Data, hidden variables, individual statements in a matrix or similar format) Heavy survey flow logic (fewer than 100 survey flow elements such as randomizers, blocks, and branches) noted in document Up to 4 rounds of iteration (one round of customer marked-up feedback on question content, response options, or logic that impacts 5 or more questions) Estimated Timing: ~2 weeks (1 week for design, 1 week for client review) | F19: Custom quote for survey with over 100 questions or elements, email or other triggers built in, advanced coding (javascript, API calls, HTML, etc.), multiple surveys.
C20: 6100 | D20: 8100 | E20: 9100 | F20: Custom Quote
C21: SDB-01 | D21: SDB-02 | E21: SDB-03 | F21: SDB-04
A23: Survey Build (without Design) | B23: DIY available in Qualtrics | C23: Includes programming for: 1 survey in English Up to 30 questions or elements (Embedded Data, hidden variables, individual statements in a matrix or similar format) Light display and skip logic (less than 20% of survey) Up to 5 image or video files, inserted 1-2 times each within the survey Light survey flow logic (fewer than 10 survey flow elements such as randomizers and branches) Does NOT include: Manual implementation of customer-provided translations Programming of typing tools Custom scoring Set up of quotas, redirects, panel connections, email messages, or distributions Assumptions: The customer is responsible for providing a fully written out questionnaire, including demographics and screener questions. Bullets or partially written questions will require design services and an additional cost. The provided documentation includes all questions, response options, logic requirements, and validation instructions (items not specified are not guaranteed to be within project scope). There will be no significant changes to the questionnaire or project requirements before or during the project. (Additional changes or significant back and forth may increase the cost and extend the timeline.) After the Qualtrics test link is shared, the customer may request up to a total of 2 hours of additional programming changes (new wording, logic, etc.). Changes after this point will require additional scoping and fees. All corrections (programmer errors) will be addressed and do not count toward these programming hours. Only existing platform functionality will be used. Requests that are outside of platform functionality or require custom coding may require additional scoping and cost. The customer is responsible for providing any images or video files required in the correct format, resolution, dimensions, and file size. Qualtrics will not source or modify any files. Estimated Timing: 3-5 business days after finalized questionnaire is provided | D23: Includes programming for: 1 survey in English Up to 60 questions or elements (Embedded Data, hidden variables, individual statements in a matrix or similar format) Moderate display and skip logic (less than 50%) Up to 10 image or video files, inserted 1-2 times each within the survey Moderate survey flow logic (fewer than 50 survey flow elements such as randomizers and branches) Does NOT include: Manual implementation of customer-provided translations Programming of typing tools Custom scoring Set up of quotas, redirects, panel connections, email messages, or distributions Assumptions: The customer is responsible for providing a fully written out questionnaire, including demographics and screener questions. Bullets or partially written questions will require design services and an additional cost. The provided documentation includes all questions, response options, logic requirements, and validation instructions (items not specified are not guaranteed to be within project scope). There will be no significant changes to the questionnaire or project requirements before or during the project. (Additional changes or significant back and forth may increase the cost and extend the timeline.) After the Qualtrics test link is shared, the customer may request up to a total of 3 hours of additional programming changes (new wording, logic, etc.). Changes after this point will require additional scoping and fees. All corrections (programmer errors) will be addressed and do not count toward these programming hours. Only existing platform functionality will be used. Requests that are outside of platform functionality or require custom coding may require additional scoping and cost. The customer is responsible for providing any images or video files required in the correct format, resolution, dimensions, and file size. Qualtrics will not source or modify any files. Estimated Timing: 5-7 business days after finalized questionnaire is provided | E23: Includes programming for: 1 survey in English Up to 100 questions or elements (Embedded Data, hidden variables, individual statements in a matrix or similar format) Moderate display and skip logic (less than 50%) Up to 12 image or video files, inserted 1-2 times each within the survey Heavy survey flow logic (fewer than 100 survey flow elements such as randomizers and branches) Does NOT include: Manual implementation of customer-provided translations Programming of typing tools Custom scoring Set up of quotas, redirects, panel connections, email messages, or distributions Assumptions: The customer is responsible for providing a fully written out questionnaire, including demographics and screener questions. Bullets or partially written questions will require design services and an additional cost. The provided documentation includes all questions, response options, logic requirements, and validation instructions (items not specified are not guaranteed to be within project scope). There will be no significant changes to the questionnaire or project requirements before or during the project. (Additional changes or significant back and forth may increase the cost and extend the timeline.) After the Qualtrics test link is shared, the customer may request up to a total of 4 hours of additional programming changes (new wording, logic, etc.). Changes after this point will require additional scoping and fees. All corrections (programmer errors) will be addressed and do not count toward these programming hours. Only existing platform functionality will be used. Requests that are outside of platform functionality or require custom coding may require additional scoping and cost. The customer is responsible for providing any images or video files required in the correct format, resolution, dimensions, and file size. Qualtrics will not source or modify any files. Estimated Timing: 7-10 business days after finalized questionnaire is provided | F23: Custom quote for survey with over 100 questions or elements, email or other triggers built in, advanced coding (javascript, API calls, etc.), multiple surveys.
B24: https://www.qualtrics.com/support/survey-platform/survey-module/survey-module-overview/ | C24: 2000 | D24: 3500 | E24: 6000 | F24: Custom Quote
C25: SBU-01 | D25: SBU-02 | E25: SBU-03 | F25: SBU-03
A27: Translation (front-end) | B27: N/A | C27: Anglicization (per word) and no link check. Tier 1 Languages: UK English Assumptions: English is the source language. | D27: Translation per word and link check for the languages below Tier 2 Languages: Chinese Simplified Chinese Traditional Czech French CA French EU French-CA German Greek Hungarian Italian Polish Portuguese (BZ) Portuguese (EU) Russian Slovak Slovenian Spanish (EU) Spanish Mexican Spanish Universal Assumptions: English is the source language. | E27: Translation per word and link check for the languages below Tier 3 Languages: All other languages not in Tier 1 or Tier 2. Some more common ones include: Arabic Croatian Danish Dutch Filipino Hebrew Hindi Indonesian Japanese Norwegian Thai Turkish Urdu Vietnamese Assumptions: English is the source language. | F27: Custom quote required if the survey has many embedded data or highlighters which require translation, materials of than the survey require translation, or other abnormal asks.
A28: Note: all costs assume English into the language. If translating a foreign language into English, add 8 cents/word | C28: $0.14/word | D28: $0.53/word + $125 per 2500 words (or parts thereof) | E28: $0.63/word + $150 per 2500 words (or parts thereof) | F28: Custom Quote
C29: TFE-01 | D29: TFE-02 | E29: TFE-03 | F29: TFE-04
A31: Typing Tool Programming | B31: N/A | C31: Includes programming for 1 typing tool, consisting of: 1 model Up to 6 segments Up to 20 input variables No additional processing steps outside of standard segment calculation (variable recoding, segment value calculation, probability calculation, and finding maximum for segment assignment) Assumptions: Model uses linear discriminant analysis consisting of coefficients per segmentation variable and segment, as well as probability calculations. Any tool with different output from this will require additional scoping and costs. Timing Estimate: 3-5 business days | D31: Includes programming for 1 typing tool, consisting of: 1 model Up to 10 segments Up to 40 input variables Up to 3 additional processing steps outside of standard segment calculation (variable recoding, segment value calculation, probability calculation, and finding maximum for segment assignment) Assumptions: Model uses linear discriminant analysis consisting of coefficients per segmentation variable and segment, as well as probability calculations. Any tool with different output from this will require additional scoping and costs. Timing Estimate: 5-7 business days | F31: Custom quote required if: Multiple models More than 10 segments More than 50 input variables Many additional post segment processing steps
C32: 3000 | D32: 5000 | F32: Custom Quote
C33: TTP-01 | D33: TTP-02 | F33: TTP-04
A35: Data Migration | B35: N/A | C35: Migration of data from a previous survey or other data source. File requirements: Migration file must be in a flat file format (CSV, TSV) There must be one response per row, and all of the information about the respondent must be contained in only that row (one respondent's information cannot be in multiple rows). All non-open end data is provided in numeric format (e.g., Male = 1, Female = 2). There must be mapping file included (a detailed survey doc that aligns with the file fields works)
C36: Custom Quote

Sheet Ad-Hoc | Reporting & Analytics
A1: XFC
A3: Ad-Hoc | Reporting & Analytics | C3: Any work required by our clients post-data collection to ensure the data is digestible and actionable. This work typically include scrubbing the data for quality, coding open-end text responses, delivering data tables/cross-tabs, or building a report or dashboard. | G3: Return to Home
B6: XM Solution | C6: Tier 1 - Standard | D6: Tier 2 - Standard Plus | E6: Tier 3 - Complex | F6: Tier 4 - Custom
A7: Overview
A8: Data Processing & Reporting
A9: Weighting | B9: DIY available in Qualtrics | C9: Qualtrics will weight the response data for one (1) Customer survey. Such weighting will include: Simple weighting only. There will be no imputation, like hot decking. Hot deck imputation is a method for handling missing data in which each missing value is replaced with an observed response from a "similar" unit. Qualtrics performs raked weighting (or RIM weighting) or interlocked weighting (as cell-based or static weighting). Up to 6 dimensions (an interlocked example of 6 dimensions, targeting 2 overlapping variables: male 18-34, female 18-34, male 35-54, female 35-54, male 55+, female 55+). 1 dataset: Qualtrics will not combine multiple datasets or projects. If the Customer wants to combine the datasets or projects, they must do so themselves, and in a way that will work for the selected weighting scheme. The Customer is responsible for ensuring that the combined dataset will operate correctly in the Qualtrics platform. 1 application: Qualtrics weighting shall involve the one-time application of a single weighting scheme. Customer may request additional iterations of applied weighting schemes for an additional fee. The weighting scheme will be applied to the dataset and cannot vary by question or be adjusted in any way by question. Qualtrics will not weight datasets that contain any type of MaxDiff or Conjoint exercises. If the dataset contains multiple waves/ time series, those should be considered in the weighting scheme and as part of the dimensions listed above. A single weighting scheme shall be applied to the entire dataset (e.g., for a 3-wave project, a single weighting scheme shall be applied to wave 1, wave 2, and wave 3). Any wave-specific differences must fall within the allotted 6 dimensions (e.g., wave 1 females = 10%, wave 1 males = 15%; wave 2 females = 25%, wave 2 males = 25%; wave 3 females = 15%, wave 3 males = 10%). Customer Responsibilities: Determine the type of weighting that applies to their needs (raked or interlocked). Should the Customer require consultation on this, Qualtrics can scope with the data science team for pricing, and advise on anticipated impact on timeline. Provide the weighting scheme that specifies the target distribution for each segment. Depending on the weighting type the Customer has selected, the Customer's weighting scheme must meet all necessary requirements for that particular weighting scheme. For example, for cell-based weighting, the target distributions for all segments should sum to 100. Missing information may impact timelines. Provide the base sizes for each of the weighting buckets. For example, for dimension 1, n=101; for dimension 2, n=37; for dimension 3, n=254; etc. Assumptions: Qualtrics may choose to weight the data within or outside of the Qualtrics platform. If the data is weighted outside of the platform, the Customer may request Qualtrics to import weights for an additional fee. If Qualtrics is conducting analysis on the weighted dataset, the data must be reimported into Qualtrics or cross-tabs must be scoped/ purchased. Qualtrics will report on weighted results, not the unweighted results. Customer may request Qualtrics to provide both weighted and unweighted analysis, for an additional fee. Due to randomization, skip logic/display logic, or skipped questions, there may be data that are missing by design. If the Customer wants to impute these missing data, such will be subject to additional costs and further scoping by Qualtrics. | D9: Qualtrics will weight the response data for one (1) Customer survey. Such weighting will include: Simple weighting only. There will be no imputation, like hot decking. Hot deck imputation is a method for handling missing data in which each missing value is replaced with an observed response from a "similar" unit. Qualtrics performs raked weighting (or RIM weighting) or interlocked weighting (as cell-based or static weighting). Between 7 and 12 dimensions (an interlocked example of 6 dimensions, targeting 2 overlapping variables: male 18-34, female 18-34, male 35-54, female 35-54, male 55+, female 55+). 1 dataset: Qualtrics will not combine multiple datasets or projects. If the Customer wants to combine the datasets or projects, they must do so themselves, and in a way that will work for the selected weighting scheme. The Customer is responsible for ensuring that the combined dataset will operate correctly in the Qualtrics platform. 1 application: Qualtrics weighting shall involve the one-time application of a single weighting scheme. Customer may request additional iterations of applied weighting schemes for an additional fee. The weighting scheme will be applied to the dataset and cannot vary by question or be adjusted in any way by question. Qualtrics will not weight datasets that contain any type of MaxDiff or Conjoint exercises. If the dataset contains multiple waves/ time series, those should be considered in the weighting scheme and as part of the dimensions listed above. A single weighting scheme shall be applied to the entire dataset (e.g., for a 3-wave project, a single weighting scheme shall be applied to wave 1, wave 2, and wave 3). Any wave-specific differences must fall within the allotted 6 dimensions (e.g., wave 1 females = 10%, wave 1 males = 15%; wave 2 females = 25%, wave 2 males = 25%; wave 3 females = 15%, wave 3 males = 10%). Customer Responsibilities: Determine the type of weighting that applies to their needs (raked or interlocked). Should the Customer require consultation on this, Qualtrics can scope with the data science team for pricing, and advise on anticipated impact on timeline. Provide the weighting scheme that specifies the target distribution for each segment. Depending on the weighting type the Customer has selected, the Customer's weighting scheme must meet all necessary requirements for that particular weighting scheme. For example, for cell-based weighting, the target distributions for all segments should sum to 100. Missing information may impact timelines. Provide the base sizes for each of the weighting buckets. For example, for dimension 1, n=101; for dimension 2, n=37; for dimension 3, n=254; etc. Assumptions: Qualtrics may choose to weight the data within or outside of the Qualtrics platform. If the data is weighted outside of the platform, the Customer may request Qualtrics to import weights for an additional fee. If Qualtrics is conducting analysis on the weighted dataset, the data must be reimported into Qualtrics or cross-tabs must be scoped/ purchased. Qualtrics will report on weighted results, not the unweighted results. Customer may request Qualtrics to provide both weighted and unweighted analysis, for an additional fee. Due to randomization, skip logic/display logic, or skipped questions, there may be data that are missing by design. If the Customer wants to impute these missing data, such will be subject to additional costs and further scoping by Qualtrics. | E9: Qualtrics will weight the response data for one (1) Customer survey. Such weighting will include: Simple weighting only. There will be no imputation, like hot decking. Hot deck imputation is a method for handling missing data in which each missing value is replaced with an observed response from a "similar" unit. Qualtrics performs raked weighting (or RIM weighting) or interlocked weighting (as cell-based or static weighting). Between 13 and 20 dimensions (an interlocked example of 6 dimensions, targeting 2 overlapping variables: male 18-34, female 18-34, male 35-54, female 35-54, male 55+, female 55+). 1 dataset. Qualtrics will not combine multiple datasets or projects. If the Customer wants to combine the datasets or projects, they must do so themselves, and in a way that will work for the selected weighting scheme. The Customer is responsible for ensuring that the combined dataset will operate correctly in the Qualtrics platform. 1 application: Qualtrics weighting shall involve the one-time application of a single weighting scheme. Customer may request additional iterations of applied weighting schemes for an additional fee. The weighting scheme will be applied to the dataset, and cannot vary by question or be adjusted in any way by question. Qualtrics will not weight datasets that contain any type of MaxDiff or Conjoint exercises. If the dataset contains multiple waves/ time series, those should be considered in the weighting scheme and as part of the dimensions listed above. A single weighting scheme shall be applied to the entire dataset (e.g., for a 3-wave project, a single weighting scheme shall be applied to wave 1, wave 2, and wave 3). Any wave-specific differences must fall within the allotted 6 dimensions (e.g., wave 1 females = 10%, wave 1 males = 15%; wave 2 females = 25%, wave 2 males = 25%; wave 3 females = 15%, wave 3 males = 10%). Customer Responsibilities: Determine the type of weighting that applies to their needs (raked or interlocked). Should the Customer require consultation on this, Qualtrics can scope with the data science team for pricing, and advise on anticipated impact on timeline. Provide the weighting scheme that specifies the target distribution for each segment. Depending on the weighting type the Customer has selected, the Customer's weighting scheme must meet all necessary requirements for that particular weighting scheme. For example, for cell-based weighting, the target distributions for all segments should sum to 100. Missing information may impact timelines. Provide the base sizes for each of the weighting buckets. For example, for dimension 1, n=101; for dimension 2, n=37; for dimension 3, n=254; etc. Assumptions: Qualtrics may choose to weight the data within or outside of the Qualtrics platform. If the data is weighted outside of the platform, the Customer may request Qualtrics to import weights for an additional fee. If Qualtrics is conducting analysis on the weighted dataset, the data must be reimported into Qualtrics or cross-tabs must be scoped/ purchased. Qualtrics will report on weighted results, not the unweighted results. Customer may request Qualtrics to provide both weighted and unweighted analysis, for an additional fee. Due to randomization, skip logic/display logic, or skipped questions, there may be data that are missing by design. If the Customer wants to impute these missing data, such will be subject to additional costs and further scoping by Qualtrics. | F9: Customer weighting on 20+ dimenstions or there is the need for multiple data sets, historical calibrations, advanced nested weights, two-step weights, three-step weights, brand assignment weights, etc.
B10: https://www.qualtrics.com/support/survey-platform/data-and-analysis-module/response-weighting/ | C10: 800 | D10: 1250 | E10: 1600 | F10: Custom Quote
C11: WTG-01 | D11: WTG-02 | E11: WTG-03 | F11: WTG-04
A13: Crosstabs | B13: DIY available in Qualtrics | C13: Qualtrics will provide crosstabs for one (1) Customer survey. Basic tables for a 10 minute survey, including: Tables with minimal routing/filters Summary tables for rating and numeric questions Single country or multi-country with same routing/filters along with same layout Banner plan options include the following; the Customer must select which one they want, and this must be reflected in the statement of work: Up to 2 banners with simple banner definitions (derived from direct questions or embedded data fields), with up to 10 banner points each Customer Responsibilities: If Qualtrics is not supporting any other reporting deliverables, the Customer is expected to provide the banner plan. If Qualtrics is supporting with reporting deliverables, Qualtrics will propose a banner plan for Customer review and approval. Assumptions: A banner refers to a master cut of data (e.g., age, gender, income) and the banner points correspond to the variables within each cut (e.g., age ranges like the following would equate to 6 banner points <18, 18-24, 25-34, 35-44, 45-54, 55+). Banner points will pull either from (a) questions that are single-select, and therefore create mutually-exclusive answer categories, or (b) variables that use question answers to create mutually-exclusive categories. Qualtrics will not stat test overlapping categories. Such cross tabs will not include open end coding. Customer survey is 10 minutes or less (as determined by median LOI). Surveys with a median LOI of longer than 10 minutes may result in impact to both timelines and cost. Cross tabs will be provided in English. Stat testing will be performed at 95% confidence level, unless otherwise specified in the analysis plan. Qualtrics will use t-tests for means, and Z-tests for percentages. Qualtrics does not perform any additional statistical testing or adjustments to statistical testing for differences across 3+ groups (ANOVAs, chi-squared tests, etc.). Qualtrics also does not report on specific statistical values (e.g., p-values, Z scores) for individual tests or report any additional information (e.g., error bars); Qualtrics only reports if the difference between the groups is statistically significant or not. Qualtrics does not do any additional adjustments beyond this reporting, unless otherwise specified. Any non-standard statistical testing may result in additional costs or implications to timeline. Should Customer requests edits after the analysis plan is already approved, such will be subject to additional costs and further scoping by Qualtrics, including amending the agreed-upon timelines for the project deliverables. Estimated Timing: 2-4 business days | D13: Qualtrics will provide crosstabs for one (1) Customer survey. Basic tables for a 15 minute survey, including: Tables with minimal routing/filters Summary tables for rating and numeric questions Single country or multi-country with same routing/filters along with same layout Banner plan options include the following; the Customer must select which one they want, and this must be reflected in the statement of work: Up to 3 banners with simple banner definitions (derived from direct questions or embedded data fields), with up to 10 banner points each Customer Responsibilities: If Qualtrics is not supporting any other reporting deliverables, the Customer is expected to provide the banner plan. If Qualtrics is supporting with reporting deliverables, Qualtrics will propose a banner plan for Customer review and approval. Assumptions: A banner refers to a master cut of data (e.g., age, gender, income) and the banner points correspond to the variables within each cut (e.g., age ranges like the following would equate to 6 banner points <18, 18-24, 25-34, 35-44, 45-54, 55+). Banner points will pull either from (a) questions that are single-select, and therefore create mutually-exclusive answer categories, or (b) variables that use question answers to create mutually-exclusive categories. Qualtrics will not stat test overlapping categories. Such cross tabs will not include open end coding. Customer survey is 15 minutes or less (as determined by median LOI). Surveys with a median LOI of longer than 15 minutes may result in impact to both timelines and cost. Cross tabs will be provided in English. Stat testing will be performed at 95% confidence level, unless otherwise specified in the analysis plan. Qualtrics will use t-tests for means, and Z-tests for percentages. Qualtrics does not perform any additional statistical testing or adjustments to statistical testing for differences across 3+ groups (ANOVAs, chi-squared tests, etc.). Qualtrics also does not report on specific statistical values (e.g., p-values, Z scores) for individual tests or report any additional information (e.g., error bars); Qualtrics only reports if the difference between the groups is statistically significant or not. Qualtrics does not do any additional adjustments beyond this reporting, unless otherwise specified. Any non-standard statistical testing may result in additional costs or implications to timeline. Should Customer requests edits after the analysis plan is already approved, such will be subject to additional costs and further scoping by Qualtrics, including amending the agreed-upon timelines for the project deliverables. Estimated Timing: 3-4 business days | E13: Qualtrics will provide crosstabs for one (1) Customer survey. Basic tables for a 20 minute survey, including: Tables with minimal routing/filters Summary tables for rating and numeric questions Single country or multi-country with same routing/filters along with same layout Banner plan options include the following; the Customer must select which one they want, and this must be reflected in the statement of work: Up to 4 banners with simple banner definitions (derived from direct questions or embedded data fields), with up to 10 banner points each Customer Responsibilities: If Qualtrics is not supporting any other reporting deliverables, the Customer is expected to provide the banner plan. If Qualtrics is supporting with reporting deliverables, Qualtrics will propose a banner plan for Customer review and approval. Assumptions: A banner refers to a master cut of data (e.g., age, gender, income) and the banner points correspond to the variables within each cut (e.g., age ranges like the following would equate to 6 banner points <18, 18-24, 25-34, 35-44, 45-54, 55+). Banner points will pull either from (a) questions that are single-select, and therefore create mutually-exclusive answer categories, or (b) variables that use question answers to create mutually-exclusive categories. Qualtrics will not stat test overlapping categories. Such cross tabs will not include open end coding. Customer survey is 20 minutes or less (as determined by median LOI). Surveys with a median LOI of longer than 20 minutes may result in impact to both timelines and cost. Cross tabs will be provided in English. Stat testing will be performed at 95% confidence level, unless otherwise specified in the analysis plan. Qualtrics will use t-tests for means, and Z-tests for percentages. Qualtrics does not perform any additional statistical testing or adjustments to statistical testing for differences across 3+ groups (ANOVAs, chi-squared tests, etc.). Qualtrics also does not report on specific statistical values (e.g., p-values, Z scores) for individual tests or report any additional information (e.g., error bars); Qualtrics only reports if the difference between the groups is statistically significant or not. Qualtrics does not do any additional adjustments beyond this reporting, unless otherwise specified. Any non-standard statistical testing may result in additional costs or implications to timeline. Should Customer requests edits after the analysis plan is already approved, such will be subject to additional costs and further scoping by Qualtrics, including amending the agreed-upon timelines for the project deliverables. Estimated Timing: 5+ business days | F13: Custom tables required for longer surveys, mulitple surveys, advanced table logic, multi-country with differences, above 50% change between waves, tables for appended data/customer data added after data collection, and more than 2 banners. | G13: m
B14: https://www.qualtrics.com/support/survey-platform/data-and-analysis-module/cross-tabulation/cross-tabulation-overview/ | C14: 2500 | D14: 3250 | E14: 4000 | F14: Custom Quote
C15: XTB-01 | D15: XTB-02 | E15: XTB-03 | F15: XTB-04
A17: Reporting | B17: DIY available in Qualtrics | C17: Qualtrics will provide one (1) report for Customer. Such a report will include: Up to 30 slides in English, covering: - Background/methodology - Key findings - Support detail grouped by themes of content - Appendix (if necessary) 1 master cut of data OR 1 cut of sub-segments (e.g., age, gender, income), with no more than 7 values per variable to be charted and stat tested in the report (as interesting and of note). Additional cuts can be included in cross-tabs (if purchased). Stat testing can be called out for up to 2 banner points of interest indicated in the headline or as a call out on the slide (e.g., banner = age and banner point = Gen Z) and compared to total respondents (e.g., 70% of respondents are aware of brand A; women are significantly more aware of brand A than men (90% vs. 50%)). Any statistical significance testing must operate under the same conditions discussed in the Crosstabs section (i.e., Qualtrics will not stat test overlapping categories). 1 country (not multinational) 1 dataset (no combining of multiple datasets or projects) Targeted statistical significance testing (optional). Qualtrics will annotate statistical significance across 1 cut of sub-groups as defined/ agreed upon in the analysis plan. This could include brands, age ranges, user types, but is limited to one 'master cut'. Other statistical significance testing is available in cross-tabs (if purchased). Unless otherwise agreed upon and accounted for in scope and timeline, such a report will not include: Nested cuts (i.e., age nested within gender: male 18-34, female 18-34, etc.). Open end coding Cross tabs Drivers, regression, or any advanced analytics Delivery Team Responsibilities: Conduct initial discovery call with Customer to determine and outline Customer report needs, including relevant questions, cuts, formatting, styles, etc. Create an analysis plan that details all report sections, questions, and cuts and share with Customer for review. Implement Customer feedback on the analysis plan and iterate for up to 2 rounds of feedback revisions. Conduct analysis and build report. Conduct Quality Assurance (QA) on the accuracy of the data as charted/ narrative as written in the presentation to ensure it accurately reflects the detail in the agreed upon analysis plan. Deliver report to Customer. If requested by Customer, Qualtrics will walk through the results (in one presentation of up to 1 hour) over online call. Customer Responsibilities: Provide report inputs (including specific metrics or design preferences) requested by Qualtrics related to study goals. Articulate any initial hypotheses that need to be tested/ validated in the analysis. Provide the sub-groups or master cuts of interest. Provide all image files (e.g., brand logo) as needed for the report. Assumptions: Qualtrics will not be obligated to begin analysis or reporting until Customer has provided written sign off on the analysis plan and Customer’s sample has finished collecting. After analysis and reporting have started, changes requested by Customer may be subject to fees and further scoping by Qualtrics. If market is a desired cut, survey content must be 90% consistent between markets. Less than 90% consistency will be subject to additional costs and further scoping by Qualtrics. Report will be provided as a .ppt using a Qualtrics template. Report requires purchase of either Survey Design or Survey Review and Consultation. Qualtrics will deliver one (1) report after all of the Customer's waves of sample have been collected (for a total of 1 report). Qualtrics will accommodate updates/ changes to the report deliverable to the extent that the requests do not conflict with what was agreed upon in the analysis plan and do not incur more than 4 additional hours of analyst time to update. These requests must be submitted within 2 weeks of initial delivery of the report. Due to randomization, skip logic/display logic, or skipped questions, there may be data that are missing by design. If Customer wants to impute these missing data, this will be subject to additional costs and further scoping by Qualtrics. At Qualtrics, the standard practice for statistical testing is to test at the 95% confidence level, unless otherwise specified in the analysis plan. We use t-tests for means, and Z-tests for percentages. We do not do any additional statistical testing or adjustments to statistical testing for differences across 3+ groups (ANOVAs, chi-squared tests, etc.). We also do not report on specific statistical values (e.g., p-values, Z scores) for individual tests or report any additional information (e.g. error bars); we only report if the difference between the groups is statistically significant or not. For example, when Qualtrics reports out on differences between (A) 18 to 24 year olds, (B) 25 to 34 year olds, and (C) 35 + year olds, we use pairwise tests to examine differences between A and B, B and C, and A and C, and report on those observed differences. Qualtrics does not do any additional adjustments beyond this reporting, unless otherwise specified in the analysis plan. If Customer would like Qualtrics to (a) test at a level other than 95%, (b) to perform any additional adjustments to the pairwise tests, or (c) report out on individual p-values from t-tests or Z-tests, this request should be disclosed by Customer during the analysis plan stage of the project. Any non-standard statistical testing may result in additional costs or implications to timeline. Should Customer request edits after the analysis plan is already approved, such will be subject to additional costs and further scoping by Qualtrics, including amending the agreed-upon timelines for the project deliverables. Estimated Timing: 10-12 business days ` | D17: Qualtrics will provide one (1) report for Customer. Such a report will include: Up to 50 slides in English, covering: - Background/methodology - Key findings - Support detail grouped by themes of content - Appendix (if necessary) Up to 2 master cuts of data or sub-segments (e.g., age, gender, income), with no more than 7 values per variable to be charted and stat tested in the report (as interesting and of note). Additional cuts may be included in the cross-tabs. Up to 2 banner points of interest indicated in the headline or as a call out on the slide (e.g., banner = age and banner point = Gen Z) and compared to total respondents 1 country (not multinational) 1 dataset (no combining of multiple datasets or projects) Targeted statistical significance testing (optional). Qualtrics will annotate statistical significance across 21 cuts of sub-groups as defined/ agreed upon in the analysis plan. This could include brands, age ranges, user types, but is limited to one 'master cut'. Other statistical significance testing is available in cross-tabs. Unless otherwise agreed, such a report will not include: Nested cuts (i.e., age nested within gender: male 18-34, female 18-34, etc.) Open end coding Cross tabs Drivers, regression, or any advanced analytics Delivery Team Responsibilities: Conduct initial discovery call with Customer to determine and outline Customer report needs, including relevant questions, cuts, formatting, styles, etc. Create an analysis plan that details all report sections, questions, and cuts and share with Customer for review. Implement Customer feedback on the analysis plan and iterate as necessary. Conduct analysis and build report. Conduct Quality Assurance (QA) on the report. Deliver report to Customer. If requested by Customer, Qualtrics will walk through the results (in one presentation of up to 1 hour) over online call. Customer Responsibilities: Provide report inputs (including specific metrics or design preferences) requested by Qualtrics related to study goals. Articulate any initial hypotheses that need to be tested/ validated in the analysis. Provide the sub-groups or master cuts of interest. Provide all image files (e.g., brand logo) as needed for the report. Assumptions: Qualtrics will not be obligated to begin analysis or reporting until Customer has provided written sign off on the analysis plan and Customer’s sample has finished collecting. After analysis and reporting have started, changes requested by Customer may be subject to fees and further scoping by Qualtrics. If market is a desired cut, survey content must be 90% consistent between markets. Less than 90% consistency will be subject to additional costs and further scoping by Qualtrics. Report will be provided as a .ppt using a Qualtrics template. Report requires purchase of either Survey Design or Survey Review and Consultation. Qualtrics will deliver one (1) report after all of the Customer's waves of sample have been collected (for a total of 1 report). Qualtrics will accommodate updates/ changes to the report deliverable to the extent that the requests do not conflict with what was agreed upon in the analysis plan and do not incur more than 4 additional hours of analyst time to update. These requests must be submitted within 2 weeks of initial delivery of the report. Due to randomization, skip logic/display logic, or skipped questions, there may be data that are missing by design. If Customer wants to impute these missing data, this will be subject to additional costs and further scoping by Qualtrics. At Qualtrics, the standard practice for statistical testing is to test at the 95% confidence level, unless otherwise specified in the analysis plan. We use t-tests for means, and Z-tests for percentages. We do not do any additional statistical testing or adjustments to statistical testing for differences across 3+ groups (ANOVAs, chi-squared tests, etc.). We also do not report on specific statistical values (e.g., p-values, Z scores) for individual tests or report any additional information (e.g. error bars); we only report if the difference between the groups is statistically significant or not. For example, when Qualtrics reports out on differences between (A) 18 to 24 year olds, (B) 25 to 34 year olds, and (C) 35 + year olds, we use pairwise tests to examine differences between A and B, B and C, and A and C, and report on those observed differences. Qualtrics does not do any additional adjustments beyond this reporting, unless otherwise specified in the analysis plan. If Customer would like Qualtrics to (a) test at a level other than 95%, (b) to perform any additional adjustments to the pairwise tests, or (c) report out on individual p-values from t-tests or Z-tests, this request should be disclosed by Customer during the analysis plan stage of the project. Any non-standard statistical testing may result in additional costs or implications to timeline. Should Customer request edits after the analysis plan is already approved, such will be subject to additional costs and further scoping by Qualtrics, including amending the agreed-upon timelines for the project deliverables. Estimated Timing: 12-15 business days | E17: Qualtrics will provide one (1) report for Customer. Such a report will include: Up to 70 slides in English, covering: - Background/methodology - Key findings - Support detail grouped by themes of content - Appendix (if necessary) Up to 3 master cuts of data or sub-segments (e.g., age, gender, income), with no more than 7 values per variable to be charted and stat tested in the report (as interesting and of note). Additional cuts may be included in the cross-tabs. 1 country (not multinational) 1 dataset (no combining of multiple datasets or projects) Targeted statistical significance testing (optional). Qualtrics will annotate statistical significance across 3 cuts of sub-groups as defined/ agreed upon in the analysis plan. This could include brands, age ranges, user types, but is limited to one 'master cut'. Other statistical significance testing is available in cross-tabs. Unless otherwise agreed, such a report will not include: Nested cuts (i.e., age nested within gender: male 18-34, female 18-34, etc.) Open end coding Cross tabs Drivers, regression, or any advanced analytics Delivery Team Responsibilities: Conduct initial discovery call with Customer to determine and outline Customer report needs, including relevant questions, cuts, formatting, styles, etc. Create an analysis plan that details all report sections, questions, and cuts and share with Customer for review. Implement Customer feedback on the analysis plan and iterate as necessary. Conduct analysis and build report. Conduct Quality Assurance (QA) on the report. Deliver report to Customer. If requested by Customer, Qualtrics will walk through the results (in one presentation of up to 1 hour) over online call. Customer Responsibilities: Provide report inputs (including specific metrics or design preferences) requested by Qualtrics related to study goals. Articulate any initial hypotheses that need to be tested/ validated in the analysis. Provide the sub-groups or master cuts of interest. Provide all image files (e.g., brand logo) as needed for the report. Assumptions: Qualtrics will not be obligated to begin analysis or reporting until Customer has provided written sign off on the analysis plan and Customer’s sample has finished collecting. After analysis and reporting have started, changes requested by Customer may be subject to fees and further scoping by Qualtrics. If market is a desired cut, survey content must be 90% consistent between markets. Less than 90% consistency will be subject to additional costs and further scoping by Qualtrics. Report will be provided as a .ppt using a Qualtrics template. Report requires purchase of either Survey Design or Survey Review and Consultation. Qualtrics will deliver one (1) report after all of the Customer's waves of sample have been collected (for a total of 1 report). Qualtrics will accommodate updates/ changes to the report deliverable to the extent that the requests do not conflict with what was agreed upon in the analysis plan and do not incur more than 4 additional hours of analyst time to update. These requests must be submitted within 2 weeks of initial delivery of the report. Due to randomization, skip logic/display logic, or skipped questions, there may be data that are missing by design. If Customer wants to impute these missing data, this will be subject to additional costs and further scoping by Qualtrics. At Qualtrics, the standard practice for statistical testing is to test at the 95% confidence level, unless otherwise specified in the analysis plan. We use t-tests for means, and Z-tests for percentages. We do not do any additional statistical testing or adjustments to statistical testing for differences across 3+ groups (ANOVAs, chi-squared tests, etc.). We also do not report on specific statistical values (e.g., p-values, Z scores) for individual tests or report any additional information (e.g. error bars); we only report if the difference between the groups is statistically significant or not. For example, when Qualtrics reports out on differences between (A) 18 to 24 year olds, (B) 25 to 34 year olds, and (C) 35 + year olds, we use pairwise tests to examine differences between A and B, B and C, and A and C, and report on those observed differences. Qualtrics does not do any additional adjustments beyond this reporting, unless otherwise specified in the analysis plan. If Customer would like Qualtrics to (a) test at a level other than 95%, (b) to perform any additional adjustments to the pairwise tests, or (c) report out on individual p-values from t-tests or Z-tests, this request should be disclosed by Customer during the analysis plan stage of the project. Any non-standard statistical testing may result in additional costs or implications to timeline. Should Customer request edits after the analysis plan is already approved, such will be subject to additional costs and further scoping by Qualtrics, including amending the agreed-upon timelines for the project deliverables. Estimated time: 14-18 business days | F17: Custom reporting for additional slides, addition cuts or nested cuts, custom stat testing needs, additional drivers, combining data from 3+ projects, non-traditional formats, etc.
B18: https://www.qualtrics.com/support/survey-platform/reports-module/results-section/reports-overview/ | C18: 11500 | D18: 16500 | E18: 21500 | F18: Custom Quote
A19: *Bundled with Review OR Design / Build | C19: 10000 | D19: 15000 | E19: 20000
C20: REP-01 | D20: REP-02 | E20: REP-03 | F20: REP-04
A22: Executive Summary | B22: DIY available in Qualtrics | D22: 1 report, including: Up to 10 slides in English Key findings 1 cut of data or sub-segments 1 country (not multi-national) 1 dataset (no combining of multiple datasets or projects) Stat testing available Assumptions: Client provides an outline of slides they want included (NPS, imagery statements, brand funnel, etc.) Does not include drivers or any advanced analytics Does not include open end coding Report will be provided as a .ppt using a Qualtrics template Report requires purchase of either Survey Design or Survey Review and Consultation. Estimated Timing: 5-7 business days | E22: 1 report, including: Up to 10 slides in English Key findings 1 cut of data or sub-segments 1 country (not multi-national) 1 dataset (no combining of multiple datasets or projects) Stat testing available Assumptions: Qualtrics reviews the data to determine outline of executive summary Does not include drivers or any advanced analytics Does not include open end coding Report will be provided as a .ppt using a Qualtrics template Report requires purchase of either Survey Design or Survey Review and Consultation. Estimated Timing: 7-9 business days | F22: Custom reporting for additional slides, addition cuts or nested cuts, custom stat testing needs, additional drivers, combining data from 3+ projects, non-traditional formats, etc.
B23: https://www.qualtrics.com/support/survey-platform/reports-module/results-section/reports-overview/ | D23: 5000 | E23: 10000 | F23: Custom Quote
C24: EXE-01 | D24: EXE-02 | E24: EXE-03 | F24: EXE-04
A26: Dashboards | B26: DIY available in Qualtrics | C26: Includes programming for: 1 dashboard in English 1 data source (e.g., surveys) Up to 30 fields 1 widget per field Up to 10 filters Up to 10 custom metrics (CX only) Up to 3 user roles Does NOT include: Advanced widget types (Key Drivers, Pivot Table, etc.) Weighting Open end coding Data import of past data (for trending) Data stacking Assumptions: Dashboard fields are defined as single select survey questions, response options for multi-select, rows for matrix questions, or embedded data. Creation of users and assigning user roles is the responsibility of the client. Only existing platform functionality will be used. Requests that are outside of platform functionality or require custom coding may require additional scoping and cost. Prior to programming, a dashboard plan will be created and confirmed with the customer. After the Qualtrics dashboard is built and shared for User Acceptance Testing (UAT), the customer may request up to a total of 2 hours of additional programming changes (alterations to the agreed plan). Changes after this point will require additional scoping and fees. All corrections (programmer errors) will be addressed and do not count toward these programming hours. This is a cost for the initial programming only and does not include ongoing maintenance or changes to the dashboard. Qualtrics provides survey build in addition to dashboard. Additional costs may be added if client provides survey build. Estimated Timing: 1-2 weeks | D26: Includes programming for: 1 dashboard in English Up to 2 data sources (e.g., surveys) Up to 60 fields Up to 2 widgets per field Up to 20 filters Up to 20 custom metrics (CX only) Up to 3 user roles Does NOT include: Advanced widget types (Key Drivers, Pivot Table, etc.) Weighting Open end coding Data import of past data (for trending) Data stacking Assumptions: Dashboard fields are defined as single select survey questions, response options for multi-select, rows for matrix questions, or embedded data. Creation of users and assigning user roles is the responsibility of the client. Only existing platform functionality will be used. Requests that are outside of platform functionality or require custom coding may require additional scoping and cost. Prior to programming, a dashboard plan will be created and confirmed with the customer. After the Qualtrics dashboard is built and shared for User Acceptance Testing (UAT), the customer may request up to a total of 3 hours of additional programming changes (alterations to the agreed plan). Changes after this point will require additional scoping and fees. All corrections (programmer errors) will be addressed and do not count toward these programming hours. This is a cost for the initial programming only and does not include ongoing maintenance or changes to the dashboard. Qualtrics provides survey build in addition to dashboard. Additional costs may be added if client provides survey build. Estimated Timing: 2-3 weeks | E26: Includes programming for: 1 dashboard in English Up to 2 data sources (e.g., surveys) Up to 100 fields Up to 2 widgets per field Up to 20 filters Up to 30 custom metrics Advanced widget types (Key Drivers, Pivot Table, etc.) (CX only) Up to 3 user roles Does NOT include: Weighting Open end coding Data import of past data (for trending) Data stacking Assumptions: Dashboard fields are defined as single select survey questions, response options for multi-select, rows for matrix questions, or embedded data. Creation of users and assigning user roles is the responsibility of the client. Only existing platform functionality will be used. Requests that are outside of platform functionality or require custom coding may require additional scoping and cost. Prior to programming, a dashboard plan will be created and confirmed with the customer. After the Qualtrics dashboard is built and shared for User Acceptance Testing (UAT), the customer may request up to a total of 4 hours of additional programming changes (alterations to the agreed plan). Changes after this point will require additional scoping and fees. All corrections (programmer errors) will be addressed and do not count toward these programming hours. This is a cost for the initial programming only and does not include ongoing maintenance or changes to the dashboard. Qualtrics provides survey build in addition to dashboard. Additional costs may be added if client provides survey build. Estimated Timing: 3-4 weeks | F26: Custom dashboard if additional fields, coded fields, data sources or filters required, multiple languages, custom ENG work.
B27: https://www.qualtrics.com/research-core/survey-reporting-dashboards/ | C27: 6500 | D27: 12500 | E27: 20000 | F27: Custom Quote
C28: DSH-01 | D28: DSH-02 | E28: DSH-03 | F28: DSH-04
A30: Open End Coding | B30: Text IQ in Qualtrics | C30: Qualtrics will provide open end coding services. Such open end coding services will include: Up to [X] responses [Y] open end response fields (e.g., text boxes) Responses must be: - 1-2 words in length - Common in Consumer Copy Test and Trackers (shorter, less difficult answers) - In English Assumptions: Coding of open ends is conducted outside of the Qualtrics platform and provided to Customer in .csv format. Coding can be imported to the Qualtrics platform as embedded data by Customer. Customer may request Qualtrics to import coding for an additional fee. ----------------------------------------------- | D30: Qualtrics will provide open end coding services. Such open end coding services will include: Up to [X] responses [Y] open end response fields (e.g., text boxes) Responses must be: - 1-2 sentences in length - Common in Customer Satisfaction and Employee Engagement (longer answers) - In English Assumptions: Coding of open ends is conducted outside of the Qualtrics platform and provided to Customer in .csv format. Coding can be imported to the Qualtrics platform as embedded data by Customer. Customer may request Qualtrics to import coding for an additional fee. ----------------------------------------------- | E30: Qualtrics will provide open end coding services. Such open end coding services will include: Up to [X] responses [Y] open end response fields (e.g., text boxes) Responses must be: - 1-2 sentences in length - Medical or other very technical responses - In English or in-language (non-English) coding Assumptions: Coding of open ends is conducted outside of the Qualtrics platform and provided to Customer in .csv format. Coding can be imported to the Qualtrics platform as embedded data by Customer. Customer may request Qualtrics to import coding for an additional fee. ----------------------------------------------- | F30: Custom coding schema or file delivery
B31: https://www.qualtrics.com/iq/text-iq/ | C31: $0.75 per response | D31: $1.00 per response | E31: $1.25 per response | F31: Custom Quote
C32: OEC-01 | D32: OEC-02 | E32: OEC-03 | F32: OEC-04
A34: Translations (back-end) | B34: N/A | C34: Translation per word of open ends plus uploading importing coded data into client's Qualtrics account Tier 2 Languages: Chinese Simplified Chinese Traditional Czech French CA French EU French-CA German Greek Hungarian Italian Polish Portuguese (BZ) Portuguese (EU) Russian Slovak Slovenian Spanish (EU) Spanish Mexican Spanish Universal | D34: Translation per word of open ends plus uploading importing coded data into client's Qualtrics account Tier 3 Languages: All other languages not in Tier 1 or Tier 2. Some more common ones include: Arabic Croatian Danish Dutch Filipino Hebrew Hindi Indonesian Japanese Norwegian Thai Turkish Urdu Vietnamese
C35: $0.61/word | D35: $0.71/word
C36: TBE-01 | D36: TBE-02
A38: Data Scrub | B38: N/A | C38: Scrub of 1 data set which meets the following criteria: Up to 2 scrubs performed Fewer than 5,000 completes Open ends are in English only | D38: Scrub of 1 data set which meets the following criteria: Up to 2 scrubs performed Fewer than 5,000 completes Open ends are not in English (only one langauge) | E38: Scrub of 1 data set which meets the following criteria: Up to 2 scrubs performed 5,000 - 7,999 completes Open ends are in English | F38: Scrub that includes any of the following: Multiple data sets / links Over 5,000 responses Multiple languages 3 or more scrubs
C39: =200/0.4 -> 500 | D39: =250/0.4 -> 625 | E39: 750 | F39: Custom Quote
C40: SCR-01 | D40: SCR-02 | E40: SCR-03 | F40: SCR-04
A42: Data Transposition | B42: N/A | C42: Transposing the data
C43: Custom Quote
C44: TRN-01
A46: Advanced Analytics
A47: Conjoint Design & Analysis | C47: Qualtrics will provide Conjoint design, programming, and reporting. Such a Conjoint will include: 3–7 features, each with 2–5 levels Minimal restriction logic in level pairing Report in .ppt format with key metrics for all statements for the overall population Up to 2 cuts (each with 2–3 populations) Simulator tool Assumptions: Features and levels are already decided by Customer (no consultation needed). Conjoint study and report will be provided in English only. Assumes reporting and analysis of only the Conjoint. Supplemental reporting or analysis requires the purchase of additional reporting scope. Estimated timeline: 5 days for design and programming, 10 days for analysis and reporting | D47: Qualtrics will provide Conjoint design, programming, and reporting. Such a Conjoint will include: 3–7 features, each with 2–5 levels Minimal restriction logic in level pairing Report in .ppt format with key metrics for all statements for the overall population Up to 4 cuts (each with 2–3 populations) Simulator tool Assumptions: Design consultation to decide on final features and levels, including restriction logic Conjoint study and report will be provided in English only. Assumes reporting and analysis of only the Conjoint. Supplemental reporting or analysis requires the purchase of additional reporting scope. Estimated timeline: 5 days for design and programming, 10 days for analysis and reporting | E47: Conjoint Design, Programming and Reporting which includes: 3-7 Features, each with 2-5 levels Moderate restriction logic on level pairing Design consultation to help create or eliminate features and levels, including restrictions. Or client has an excessive number of attributes that need to be paired back. Report in .ppt format with key metrics for all statements for the overall population Up to 4 cuts (each with 2–3 populations) Simulator tool Assumptions: Design consultation to decide on final features and levels, including restriction logic Conjoint study and report will be provided in English only. Assumes reporting and analysis of only the Conjoint. Supplemental reporting or analysis requires the purchase of additional reporting scope. Estimated timeline: 5 days for design and programming, 10 days for analysis and reporting | F47: Custom quote required if any of the following are required: Rushed timeline 5+ cuts or complex cuts (+$500-$1000 per additional) Design restrictions or logic (+$1000-$2000) Conjoint localized/translated into multiple languages Custom HTML incl. custom look & feel, hoverover or images (+$1000-$2000) Multiple conjoints in the same survey Translations/localizations added to the simulator/report Custom reporting (e.g., custom scaling, delivery of raw data in client supplied format)
A48: Please include Advanced Analytics on calls to confirm needs before selling. | C48: 12000 | D48: 15000 | E48: 18000 | F48: Custom Quote
C49: CON-01 | D49: CON-02 | E49: CON-03 | F49: CON-04
A51: MaxDiff Design and Reporting | C51: Qualtrics will provide MaxDiff design, programming, and reporting. Such a MaxDiff will include: 8–20 statements No restrictions or logic within the design Report in .ppt format with key metrics for all statements (preference share) for the overall population Up to 2 cuts (each with 2-3 populations) Assumptions: Statements are already decided by Customer (no consultation needed). MaxDiff study and report will be provided in English only. Assumes reporting and analysis of only the MaxDiff. Supplemental reporting or analysis requires the purchase of additional reporting scope. Estimated timeline: 5 days for design and programming, 10 days for analysis and reporting | D51: Qualtrics will provide MaxDiff design, programming, and reporting. Such a MaxDiff will include: 8–20 statements No restrictions or logic within the design Report in .ppt format with key metrics for all statements (preference share) for the overall population Up to 4 cuts (each with 2-3 populations) Assumptions: Includes consultation to finalize statements if needed MaxDiff study and report will be provided in English only. Assumes reporting and analysis of only the MaxDiff. Supplemental reporting or analysis requires the purchase of additional reporting scope. Estimated timeline: 5 days for design and programming, 10 days for analysis and reporting | E51: MaxDiff Design and Reporting which includes: 20+ statements, includes consultation to finalize statements if needed No restrictions or logic within the design MaxDiff programming PPT report with key metric (preference share) for all statements for the overall population and up to 4 cuts (each with 2-3 populations) Assumptions: Includes consultation to finalize statements if needed MaxDiff study and report will be provided in English only. Assumes reporting and analysis of only the MaxDiff. Supplemental reporting or analysis requires the purchase of additional reporting scope. Estimated Timeline: 5 days for design and programming, 10 days for analysis and reporting | F51: Custom quote required if any of the following are required: 5+ cuts or complex cuts (+$500 per additional) Design restrictions or logic (+$1000-$2000) Custom HTML incl. hoverover or images (+$1000) Multiple MaxDiffs in the same survey Translations/localizations added to the MaxDiff Custom reporting or 5+ cuts (e.g., reporting on groups of statements, custom scaling, delivery of raw data in client supplied format) Custom metrics (metric other than preference share) requires in reporting
A52: Please include Advanced Analytics on calls to confirm needs before selling. | C52: 7500 | D52: 9500 | E52: 11500 | F52: Custom Quote
C53: MXD-01 | D53: MXD-02 | E53: MXD-03 | F53: MXD-04
A55: TURF Analysis & Tool | C55: TURF Results added into a MaxDiff or Conjoint Report | D55: TURF Results added into MaxDiff or Conjoint Report and Creation of an interactive TURF Simulator
A56: Note, client must have bought MaxDiff or Conjoint to get this | C56: 2000 | D56: 3000
C57: TRF-01 | D57: TRF-02
A59: Regression Analysis | C59: OLS or Logit regression analysis for 1 DV/Outcome | F59: More advanced OLS or Logit regressions as well as SEM, Heirarchical, or more advanced regression analysis.
C60: 3000 | F60: Custom Quote
C61: REG-01 | F61: REG-04
C63: Clustering analysis and consultation based on a select number of psychographic, demographic, or behavioral variables. Includes a review of the segments with the client before reporting begins. | F63: Clustering involving appended data, client data, multiple data sets or clustering analysis that needs to be performed within a country or subgroup.
A64: *Only sold as part of segmentation research | C64: 15000 | F64: Custom
C65: CLS-01 | F65: CLS-04
A67: Typing Tool Creation (algorithm, excel, & add to Qualtrics account) | C67: Typing tool creation based on segmentation data and results. Includes creation of algorithms, creation of typing tool in Qualtrics, and creation of supporting documentation.
A68: *Only sold as part of segmentation research | C68: 5000
C69: TTC-01
A71: Market Sizing Analysis | C71: Estimating the potential size (people, volume and/or revenue) of a market and using that to understand size of segments, a particular category, or potential interest in a concept. Note, it may be required to collect partials and screenouts.
A72: *Only sold as part of A&U or segmentation research | C72: 2000
A75: Van Westendorp (VanWest, VW) | C75: Qualtrics will provide Van Westendorp programming and reporting in one (1) survey within the Customer’s account. Such design, programming, and reporting will include: One VW exercise focused on a single product/concept Calculation of acceptable price range and indifference price Analysis of elasticity for up to two (2) subgroups (e.g., a specific age range, frequent purchasers etc.) Reporting in .ppt slides including summary of results and price sensitivity Pricing for additional cuts available on request Assumptions: Pricing above is for a single product/concept; additional pricing available on request Pricing is in a single currency
C76: 4000
A79: Gabor Granger / Price Elasticity Analysis | C79: Qualtrics will provide Gabor Granger programming and reporting in one (1) survey within the Customer’s account. Such design, programming, and reporting will include: One GG exercise focused on a single product/concept Inclusion of static image and or description within the GG question text Javascript for price adaptation for one GG exercise Calculation of price elasticity and revenue proportions and optimal price Analysis of elasticity for up to two (2) subgroups (e.g., a specific age range, frequent purchasers etc.) Reporting in .ppt slides including summary of results and elasticity curve(s) Pricing for additional subgroups available upon request Assumptions: Pricing above is for a single product/concept; additional pricing available on request Pricing is in a single currency
C80: 4000
A83: Key Drivers Analysis (KDA) | C83: Qualtrics will provide a Key Drivers Analysis (KDA) in one (1) survey within the Customer’s account Such design, programming, and reporting will include: 1 model and 1 dependent variable and up to 2 subgroups. Reporting on attribute importance and variance explained Assumptions: Design has been reviewed and approved by the team prior to fielding Attributes have 50% or greater coverage in survey data for analysis $1000 per model if more than 2 cuts | D83: Qualtrics will provide a Key Drivers Analysis (KDA) in one (1) survey within the Customer’s account Such design, programming, and reporting will include: 2 models and 1 dependent variable and up to 2 subgroups. Reporting on attribute importance and variance explained Assumptions: Design has been reviewed and approved by the team prior to fielding Attributes have 50% or greater coverage in survey data for analysis $1000 per model if more than 2 cuts | E83: Qualtrics will provide a Key Drivers Analysis (KDA) in one (1) survey within the Customer’s account Such design, programming, and reporting will include: 3 models and 1 dependent variable and up to 2 subgroups. Reporting on attribute importance and variance explained Assumptions: Design has been reviewed and approved by the team prior to fielding Attributes have 50% or greater coverage in survey data for analysis $1000 per model if more than 2 cuts
C84: 7000 | D84: 9000 | E84: 11000
A86: KANO | C86: Kano Analysis Qualtrics will provide Kano design, programming, and reporting. Such design, programming, and reporting will include: Up to 25 product features Incorporation of text description or static image into question text Report in .ppt format including classification of each feature tested using discrete analysis Up to 2 cuts (each with 2–3 populations) Assumptions: Product are already provided by Customer (consultation available). Kano study and report will be provided in English only. Assumes reporting and analysis of only the Kano. Supplemental reporting or analysis requires the purchase of additional reporting scope. Estimated timeline: 5 days for design and programming, 10 days for analysis and reporting
C87: 15000

Sheet Ad-Hoc | Data Collection
A1: fma
A3: Ad-Hoc | Data Collection | C3: Disseminating the survey to a particular consumer or B2B audience by quotas, integrating with 3rd party vendors, re-directs. | G3: Return to Home
B6: XM Solution | C6: Tier 1 - Standard | D6: Tier 2 - Standard Plus | E6: Tier 3 - Advanced | F6: Tier 4 - Custom
A7: Overview
A8: Data Collection
A9: Project Management | B9: N/A | C9: TBD - not currently offered | D9: TBD - not currently offered | E9: TBD - not currently offered
C10: Price | D10: Price | E10: Price
C11: PMT-01 | D11: PMT-02 | E11: PMT-03
A13: Panel Sample - Standard | B13: N/A | C13: B2C Sample through Online Panel Partners with up to 3 quotas on completes | D13: B2C Sample through Online Panel Partners with up to 5 quotas on completes OR simple nested quotas (2 variables, gender + 1 other) | E13: B2C with Balanced Starts (up to 5 quotas on entries) or complex nested quotas (more than 2 variables)
A14: Note: Minimum is $500 per link | C14: CPI * 2.5 / complete | D14: (CPI * 2.5 + $1) / complete | E14: (CPI * 2.5 + $3) / complete
C15: PSA-01 | D15: PSA-02 | E15: PSA-03
A17: Panel Sample - B2B Sample | B17: N/A | C17: B2B Sample through Online Panel Partners with up to 3 quotas on completes
A18: Note: Minimum is $500 per link | C18: CPI * 2.5 / complete
A21: Panel Sample - Medical | B21: N/A | C21: Medical Sample through Online Panel Partners with up to 3 quotas on completes
A22: Note: Minimum is $500 per link | C22: CPI * 2.5 / complete
A25: Panel Sample - Probability Sample | B25: N/A | C25: B2C Probability Sampling for Gen Pop audience within USA
A26: Note: Minimum is $500 per link | C26: CPI * 1.54 / complete
C27: PRB-01
A29: List Send - Branded | B29: N/A | C29: Qualtrics will distribute one (1) survey to one (1) Customer list of respondents via the Qualtrics emailer. Such list management will include: Screener and quota setup (simple) Message creation (no custom HTML formatting) Up to 2 Invite distributions (e.g., soft launch group and full launch group) Up to 2 Reminders per distribution group 1 Thank You message (optional) Total list size up to 100,000 recipients, with real-time send or scheduling No SMS sends Delivery Team Responsibilities: Manage the data collection process overall. Set up and test survey quotas, screeners, and related logic, and approve the survey prior to launching to targeted respondents. This does not include reviewing additional skip logic or display logic, unless otherwise agreed. Monitor data collection and send updates to Customer during fielding. Customer Responsibilities: Provide cleaned list of respondent email addresses. Provide 'From [name]' information and 'Reply-To' email address. Provide subject lines and message text for Invites, Reminders, and Thank You in .doc or Qualtrics format. No HTML or custom formatting is permitted. Provide all image files in the correct Qualtrics compatible format, resolution, dimensions, and file size. Qualtrics will not source or modify any files. Manage all respondent requests, follow-ups, and queries. Assumptions: Qualtrics is not responsible for the response rate or quality of the list provided and is only responsible for distribution. Unless otherwise agreed, all survey list sends must originate from Customer’s Qualtrics account. Unless specified to the Qualtrics project manager before data collection begins, Qualtrics will not record partial completes for this Project in Customer’s Qualtrics account. These partial completes will not count against the total good completes (n) requested for the Project. ----------------------------------------------- | D29: *Note, if list size is over is 100,000, we may need to use Verias to clean email lists - Recommended for all countries. Required for countries outside of US, Canada, Western Europe, Australia, and New Zealand. Qualtrics will distribute one (1) survey to one (1) Customer list of respondents via the Qualtrics emailer. Such list management will include: Screener and quota setup (simple) Message creation (no custom HTML formatting) Up to 5 Invite distributions (e.g., soft launch group and full launch group) Up to 2 Reminders per distribution group 1 Thank You message (optional) Total list size up to 350,000 recipients, with real-time send or scheduling No SMS sends Delivery Team Responsibilities: Manage the data collection process overall. Set up and test survey quotas, screeners, and related logic, and approve the survey prior to launching to targeted respondents. This does not include reviewing additional skip logic or display logic, unless otherwise agreed. Monitor data collection and send updates to Customer during fielding. Customer Responsibilities: Provide cleaned list of respondent email addresses. Provide 'From [name]' information and 'Reply-To' email address. Provide subject lines and message text for Invites, Reminders, and Thank You in .doc or Qualtrics format. No HTML or custom formatting is permitted. Provide all image files in the correct Qualtrics compatible format, resolution, dimensions, and file size. Qualtrics will not source or modify any files. Manage all respondent requests, follow-ups, and queries. Assumptions: Qualtrics is not responsible for the response rate or quality of the list provided and is only responsible for distribution. Unless otherwise agreed, all survey list sends must originate from Customer’s Qualtrics account. Unless specified to the Qualtrics project manager before data collection begins, Qualtrics will not record partial completes for this Project in Customer’s Qualtrics account. These partial completes will not count against the total good completes (n) requested for the Project. | E29: *Note, if list size is over is 100,000, we may need to use Verias to clean email lists - Recommended for all countries. Required for countries outside of US, Canada, Western Europe, Australia, and New Zealand. Qualtrics will distribute one (1) survey to one (1) Customer list of respondents via the Qualtrics emailer. Such list management will include: Screener and quota setup (simple) Message creation (no custom HTML formatting) Up to 10 Invite distributions (e.g., soft launch group and full launch group) Up to 2 Reminders per distribution group 1 Thank You message (optional) Total list size up to 600,000 recipients, with real-time send or scheduling No SMS sends Delivery Team Responsibilities: Manage the data collection process overall. Set up and test survey quotas, screeners, and related logic, and approve the survey prior to launching to targeted respondents. This does not include reviewing additional skip logic or display logic, unless otherwise agreed. Monitor data collection and send updates to Customer during fielding. Customer Responsibilities: Provide cleaned list of respondent email addresses. Provide 'From [name]' information and 'Reply-To' email address. Provide subject lines and message text for Invites, Reminders, and Thank You in .doc or Qualtrics format. Provide any desired message HTML formatting. Qualtrics will not provide or modify any HTML formatting. Provide all image files in the correct Qualtrics compatible format, resolution, dimensions, and file size. Qualtrics will not source or modify any files. Manage all respondent requests, follow-ups, and queries. Assumptions: Qualtrics is not responsible for the response rate or quality of the list provided and is only responsible for distribution. Unless otherwise agreed, all survey list sends must originate from Customer’s Qualtrics account. Unless specified to the Qualtrics project manager before data collection begins, Qualtrics will not record partial completes for this Project in Customer’s Qualtrics account. These partial completes will not count against the total good completes (n) requested for the Project. ----------------------------------------------- | F29: Branded list send which is more complex than the Advanced option and may include: Multiple countries Multiple invitations for different groups Over 10 Distributions Email triggers List sends involving dyads, recontacts, or diaries
A30: Note: Costs are per link. If doing a basic list send for 2 links with 2 lists for a project, that is $3000 ($1500 x 2) | C30: 1500 | D30: $3,500 (+ 0.002/email if using Verias) | E30: $7,000 (+ 0.002/email if using Verias) | F30: Custom Quote
C31: LSB-01 | D31: LSB-02 | E31: LSB-03 | F31: LSB-04
A33: List Send - Unbranded | B33: N/A | C33: Standard invite (no custom formatting required, client provides messaging, client provides invite for unbranded invite (in Qualtrics or word)) Screener and Quota Setup included (simple) 1-2 distributions (e.g., soft launch group and full launch group), up to 2 reminders per group, and a Thank You message (optional) Total list size up to 100,000 recipients, with real-time send or scheduling. List provided is clean and ready for distribution. | D33: Same as Standard except: 3-5 distributions Note, if list size is over is 100,000, we may need to use Verias to clean email lists - Recommended for all countries. Required for countries outside of US, Canada, Western Europe, Australia, and New Zealand. Qualtrics will distribute one (1) survey to one (1) Customer list of respondents via the Qualtrics emailer. Such list management will include: Screener and quota setup (simple) Message creation (no custom HTML formatting) Up to 5 Invite distributions (e.g., soft launch group and full launch group) Up to 2 Reminders per distribution group 1 Thank You message (optional) Total list size up to 350,000 recipients, with real-time send or scheduling No SMS sends Delivery Team Responsibilities: Manage the data collection process overall. Set up and test survey quotas, screeners, and related logic, and approve the survey prior to launching to targeted respondents. This does not include reviewing additional skip logic or display logic, unless otherwise agreed. Monitor data collection and send updates to Customer during fielding. Customer Responsibilities: Provide cleaned list of respondent email addresses. Provide 'From [name]' information and 'Reply-To' email address. Provide subject lines and message text for Invites, Reminders, and Thank You in .doc or Qualtrics format. No HTML or custom formatting is permitted. Provide all image files in the correct Qualtrics compatible format, resolution, dimensions, and file size. Qualtrics will not source or modify any files. Manage all respondent requests, follow-ups, and queries. Assumptions: Qualtrics is not responsible for the response rate or quality of the list provided and is only responsible for distribution. Unless otherwise agreed, all survey list sends must originate from Customer’s Qualtrics account. Unless specified to the Qualtrics project manager before data collection begins, Qualtrics will not record partial completes for this Project in Customer’s Qualtrics account. These partial completes will not count against the total good completes (n) requested for the Project. | E33: Same as Standard Plus except: Custom invites including HTML integration - any email that includes custom HTML coding and is not just a text insertion into our product for our team 5+ distributions Over 350,000 recipients. List provided is clean and ready for distribution. | F33: Branded list send which is more complex than the Advanced option and may include: Multiple countries Multiple invitations for different groups Over 10 Distributions Email triggers List sends involving dyads, recontacts, or diaries
A34: Note: Unbranded list sends cannot be sent from a Qualtrics owned account and must still come from the client account. | C34: 2500 | D34: $4,000 (+ 0.002/email if using Verias) | E34: $7,500 (+ 0.002/email if using Verias) | F34: Custom Quote
C35: LSU-01 | D35: LSU-02 | E35: LSU-03 | F35: LSU-04
A37: Incentive Management | B37: Client handles Incentives themselves through integrations with Tango Card or Rybbon Tango: https://www.qualtrics.com/marketplace/tango-card-integration/ Rybbon: https://www.qualtrics.com/marketplace/rybbon-integration/ | C37: Sending out gift cards or other incentives to a specific list of people who completes the survey (identified through use of customer lists or PII asked in the survey) | D37: N/A | E37: N/A
B38: Included in License | C38: $1,500 or 15% of total incentive amount, whichever is greater
C39: ICM-01
A41: Sweepstake Drawings | B41: N/A | C41: Not Offered - Do Not Sell We legally cannot draw the winner
A45: 3rd Party Integration | B45: N/A | C45: Integration with or redirecting to/from a 3rd party platform. Easy integration that has been done many times before. Anything not on this list would be Tier 2. Max of 2 quotas on the overall sample. Platforms included: - Sawtooth - Millisecond/Inquisit - Dialsmith - VoxPopMe | D45: Moderate difficulty or we have never integrated before. This includes: - Custom websites that the customer built - Most Academic integrations - No other complex requirements besides passing into and out of the third party survey | E45: Difficult and complex integrations. This includes (but is not limited to): -Setups that require 2+ phone calls with the PM to scope and setup the integration -Other pieces such as multiple links that the customer is redirecting to (this includes randomization requirements, quotas on the integration etc.) -3+ quotas on overall sample -Surveys with a total LOI of 30+ minutes -Surveys where the participants spend more than 15 minutes in the third party portion -Surveys with an IR under 20%
A46: Caution, integrations will lead to drop out of 20%-30%+, resulting in lower IR and increased CPI | C46: 1500 | D46: 3000 | E46: 5000
C47: TPI-01 | D47: TPI-02 | E47: TPI-03
A49: Data Appends | B49: N/A | C49: Appending basic panel demographic data after data collection is completed. 1 time append only (if appending once partway through and again at the end, charge for this twice. However, appending Age, Gender, and Race at the same time is just 1 charge). Demographics for Tier 1 Include any or all of the following: Age Gender Education Race/ethnicity Marital status Postal code | D49: Appending demographics or panel variables after data collection is completed. 1 time append only (if appending once partway through and again at the end, charge for this twice. However, appending Age, Gender, and Race at the same time is just 1 charge). Variables included in this tier include any of the following: Tier 1 Demographics HH Income HH Size Other Household level demographics Consumer technology variables Auto variables | E49: Appending profiling variables - each data set that needs appending is at this cost. If multiple data sets are required, charge for each data set (appending Mosaic and PRIZM 5 would result in two charges). Data sets included in this tier: Household decision making panel database variables Financial and Insurance panel database variables Experian Mosaic Experian Financial segmentation solution (UK Only) Claritas PRIZM Premier (lifestyle segments) Claritas P$Cycle (financial segments) Claritas Connexions (segmentation using consumer behavior and usage from tech, video, data services) Environics PRIZM5 (Canada lifetstyle segmentation) Neustar ElementOne (172-segment segmentation driven by demos) L2 Voter Data (registration data and voter history) | F49: Appending profiling variables - each data set that needs appending is at this cost. If multiple data sets are required, charge for each data set. Business Decision Maker panel database variables Behaviors and Interests panel database variables Experian Marketing Analytics Bundle (financial, demographic, lifestyle, interest and life stage data) Experian Scorex PLUS (modeled credit scores) Axciom InfoBase - Data Bundles Axciom Personicx Full Contact Social Media (social media match and profiling data)
A50: Note: Custom quote for any topics not listed in the four buckets or anything over 5,000 responses. Note: prices reflect using Dynata as panel provider, custom quote required for other sources. | C50: $1000 per append for Dynata or Lucid | D50: $2500 per append for Dynata or Lucid | E50: $3750 per variable set appended when using Dynata | F50: $6500 per variable set appended when using Dynata
C51: DAP-01 | D51: DAP-02 | E51: DAP-03 | F51: DAP-04
A53: Panel Sample - Recontact | B53: N/A | C53: Participant takes an original survey and is later recontacted to take a second survey. Depending on the length between surveys, we typically see only 20%-40% of original participants take the second survey. No gaurentees can be made on quotas or respondent mix after the first wave.
A54: Note: must note its a recontact before first phase. Caution, problematic project type | C54: CPI * 2.5 / complete
C55: PRE-01
A57: Panel Sample - Dyad | B57: N/A | C57: A pair of participants (e.g., parent-child, manager-employee, couples) taking a survey one after the other.
A58: Caution, problematic project type | C58: CPI * 2.5 / complete
C59: PDY-01
A61: Panel Sample - CATI | B61: N/A | C61: Computer Assisted Telephone Interview, or in other words, online telephone surveys.
A62: Caution, problematic project type | C62: CPI * 2.5 / complete
C63: PCA-01
A65: Panel Sample - IHUT | B65: N/A | C65: In-home usage tests involve a company sending a product to a specific group of people to test at home and take a survey during/after that experience with the product.
A66: Caution, problematic project type | C66: CPI * 2.5 / complete
C67: PIH-01
A69: Panel Sample - Diary Study | B69: N/A | C69: Research in which the participant repeatedly takes surveys (e.g., once a day for a week or 4 times a day for 2 weeks). Qualtrics cannot guarantee the requested number of completes given the high rates of attrition on these studies.
A70: Note: Strongly Recommend ROI Rocket Caution, problematic project type | C70: CPI * 2.5 / complete
C71: PDS-01
A73: Panel Sample - Online Recruit / Panel Build | B73: N/A | C73: Qualifying participants online and collecting personal identifying information (PII), allowing the client to maintain contact with them in the future.
A74: Note: collecting PII severly limits available panelists. Note: we cannot guarantee any success rate with emails gathered | C74: CPI * 2.5 / complete + $1,000 for PM and Programming Fee
C75: POR-01
A77: Panel Sample - In-Person/Offline Custom Recruit / Panel Build | B77: N/A | C77: Not Offered - Do Not Sell
A81: TargetSmart | B81: N/A | C81: Not Offered - Do Not Sell
A85: Data Entry (manually entering data from paper surveys into Qualtrics) | B85: N/A | C85: Not Offered - Do Not Sell
A89: Panel Sample - Passive Metering | B89: N/A | C89: Data collection which involves respondents who have or asked to download software to their devices that software collects data about the clicks the panelist makes on the devices. The information about the clicks includes the app names, domain names, the unique URL, time frames, pages visited, and more.
C90: CPI * 2.5 / complete
C91: PPM-01
A93: Panel Sample - Geo-Fencing / Location Based | B93: N/A | C93: Panel sample which tracks the location of the panelist so you can track their movements and which places they have visisted or use their location to trigger surveys at certain points or events (e.g., when they leave a store)
A94: Note: using MFour Behavioral Data | C94: CPI * 2.5 / complete
C95: PGF-01

Sheet List view
B1: Category | C1: Service | D1: Tier | E1: SFDC Product Code | F1: SKU (Code+Tier) | G1: Detailed Description | H1: Legal Language | I1: Update Status | J1: Global Retail Price (to client) | K1: Bundled Price | L1: EMEA Retail Price (if blank, refer to Global) | M1: APJ Retail Price (if blank, refer to Global) | N1: Feedback from Sales | O1: NA Approval | P1: EMEA Approval | Q1: APJ Approval | R1: Unit | S1: Extra Costs | T1: Offered in NA | U1: Offered in EMEA | V1: Offered in APJ | W1: Return to Home | X1: Cost Estimate - Billed to Q | Y1: Cost Unit - Costs billed to Q | Z1: Extra Costs - Billed to Q | AA1: Estimated Staff Costs (not marked up) | AB1: Markup/margin | AC1: PM Assignment Points - OK to Start | AD1: PM Assignment Points - In Progress | AE1: Mavenlink Deliverable Template | AF1: Preferred Resource (Internal, Vendor, QPN) | AG1: Secondary Resource (Internal, Vendor, QPN) | AH1: Estimated Hours - L1/L2 PM | AI1: Estimated Hours - L3/L4 PM | AJ1: Estimated Hours - L1/L2 RS | AK1: Estimated Hours - L3/L4 RA | AL1: Estimated Hours - L5+ RM | AM1: Estimated Hours - TC | AN1: Total Estimated Staff Costs - USA | AO1: Total External Staff Costs - USA | AP1: Total Estimated Staff Costs - EMEA | AQ1: Total Estimated Staff Costs - APJ | AR1: Preferred Vendor 1 | AS1: Preferred Vendor 2 | AT1: Preferred Vendor 3 | AU1: Preferred QPN 01 | AV1: Preferred QPN 02 | AW1: Preferred QPN 03 | AX1: A&U - Standard | AY1: A&U - Standard Plus | AZ1: A&U - Advanced | BA1: A&U - Custom | BB1: Ad Testing - Standard | BC1: Ad Testing - Standard Plus | BD1: Ad Testing - Advanced | BE1: Ad Testing - Custom | BF1: Concept Testing - Standard | BG1: Concept Testing - Standard Plus | BH1: Concept Testing - Advanced | BI1: Concept Testing - Custom | BJ1: Competitive Benchmarking - Standard | BK1: Competitive Benchmarking - Standard Plus | BL1: Competitive Benchmarking - Advanced | BM1: Competitive Benchmarking - Custom | BN1: Message Testing via MaxDiff - Standard | BO1: Message Testing via MaxDiff - Standard Plus | BP1: Message Testing via MaxDiff - Advanced | BQ1: Message Testing via MaxDiff - Custom | BR1: Product Development with Conjoint - Standard | BS1: Product Development with Conjoint - Standard Plus | BT1: Product Development with Conjoint - Advanced | BU1: Product Development with Conjoint - Custom | BV1: Product Development with MaxDiff - Standard | BW1: Product Development with MaxDiff - Standard Plus | BX1: Product Development with MaxDiff - Advanced | BY1: Product Development with MaxDiff - Custom | BZ1: Segmentation - Standard | CA1: Segmentation - Custom | CD1: Maturity Level (Initial, Managed, Defined, Quantitiatively Managed, Optimizing) | CE1: Maturity: Pricing and scoping | CF1: Maturity: Legal / SOWs | CG1: Maturity: Capacity & Resource Mgmt | CH1: Maturity: Platform | CI1: Maturity: Project Execution | CJ1: Maturity: Quality/ QA/QC | CK1: Maturity: Vendors | CL1: Maturity: Systems | CM1: Maturity: Marketing | CN1: Maturity: Sales Enablement - Internal Training | CO1: Maturity: Sales Enablement - External Facing
A2: RS | B2: Ad-Hoc | Design and Build | C2: Survey Review and Consultation | D2: Standard | E2: RSSurveyRevConsult | F2: =E2&" - "&D2 -> RSSurveyRevConsult - Standard | G2: ='Ad-Hoc | Design and Build'!$C10 -> Qualtrics will review one (1) survey for Customer. Such survey review will include: Up to 30 questions (each individual statement in a matrix or similar format counts as a question) Unless otherwise agreed, such survey review will not include: Technical review or testing Survey build or survey programming edits Delivery Team Responsibilities: If necessary, conduct kick-off call to discuss research objectives. Provide methodological expertise on best design practices and technical expertise on what is feasible in the platform. Conduct Quality Assurance (QA) for Customer's survey design. Share recommendations for Customer review. Customer Responsibilities: Provide a fully written out questionnaire, including demographics and screener questions. Bullets or partially written questions will be subject to additional fees and further scoping by Qualtrics. Provide the questionnaire in a .doc file, Google Doc, or similar format. Spreadsheet formats (.xls, Google Sheets, etc.) will be subject to additional fees and further scoping by Qualtrics. Assumptions: After initial survey recommendations are shared, Customer may request up to 2 rounds of iteration for review (Customer marked-up feedback on question content, response options, or logic that impacts 5 or more questions) Estimated Timing: 3-5 business days | H2: Qualtrics will provide one (1) survey review for Customer. Such survey review will include: Up to 30 questions (individual statements in a matrix or similar format each count as a question) Such survey review will not include: Technical review or testing Survey build or survey programming edits Delivery Team Responsibilities: Provide methodological expertise on best design practices and technical expertise on what is feasible in the platform. Conduct Quality Assurance (QA) for Customer's survey design. Share recommendations for Customer review. Customer Responsibilities: Provide a fully written out questionnaire, including demographics and screener questions. Bullets or partially written questions will require design services and an additional cost. Provide the questionnaire in a .doc file, Google Doc, or similar format. Spreadsheet formats (.xls, Google Sheets, etc.) will require additional scoping and costs. Answer questions and clarify requirements as needed during project. Review Qualtrics survey recommendations and provide consolidated feedback from relevant stakeholders. Provide written sign off on final survey design. Assumptions: After initial survey recommendations are shared, Customer may request up to 2 rounds of iteration for review (Customer marked-up feedback on question content, response options, or logic that impacts 5 or more questions). | I2: Aug 18, 22: Price updated. Refer to RX Cost Normalization. | J2: ='Ad-Hoc | Design and Build'!$C11 -> 2100 | K2: ='Ad-Hoc | Design and Build'!$C12 -> 2000 | O2: Ali H. & Adam P. | P2: Conor C. & James P. | Q2: Sam B. | R2: per service | T2: Yes | U2: Yes | V2: Yes | AA2: =roundup(AN2,-1) -> 470 | AB2: 0.76 | AC2: 2 | AD2: 1 | AE2: Build Services template | AF2: Internal | AG2: Vendor | AI2: 1 | AJ2: 6 | AL2: 1 | AN2: =(AH2*'Staff Rates (Internal)'!B$2)+(AI2*'Staff Rates (Internal)'!B$3)+(AJ2*'Staff Rates (Internal)'!B$4)+(AK2*'Staff Rates (Internal)'!B$5)+(AL2*'Staff Rates (Internal)'!B$6)+(AM2*'Staff Rates (Internal)'!B$7) -> 469.5 | AO2: =(AH2*'Staff Rates (External)'!B$2)+(AI2*'Staff Rates (External)'!B$3)+(AJ2*'Staff Rates (External)'!B$4)+(AK2*'Staff Rates (External)'!B$5)+(AL2*'Staff Rates (External)'!B$6)+(AM2*'Staff Rates (External)'!B$7) -> 2100 | AR2: Y2 Analytics | AS2: Strop | CC2: =C2 -> Survey Review and Consultation | CD2: =average(CE2:CO2) -> 2.1818182 | CE2: 3 | CF2: 3 | CG2: 2 | CH2: 3 | CI2: 2 | CJ2: 3 | CK2: 2 | CL2: 3 | CM2: 1 | CN2: 1 | CO2: 1
A3: RS | B3: Ad-Hoc | Design and Build | C3: Survey Review and Consultation | D3: Standard Plus | E3: RSSurveyRevConsult | F3: =E3&" - "&D3 -> RSSurveyRevConsult - Standard Plus | G3: ='Ad-Hoc | Design and Build'!$D10 -> Qualtrics will review one (1) survey for Customer. Such survey review will include: Up to 60 questions (each individual statement in a matrix or similar format counts as a question) Unless otherwise agreed, such survey review will not include: Technical review or testing Survey build or survey programming edits Delivery Team Responsibilities: If necessary, conduct kick-off call to discuss research objectives. Provide methodological expertise on best design practices and technical expertise on what is feasible in the platform. Conduct Quality Assurance (QA) for Customer's survey design. Share recommendations for Customer review. Customer Responsibilities: Provide a fully written out questionnaire, including demographics and screener questions. Bullets or partially written questions will be subject to additional fees and further scoping by Qualtrics. Provide the questionnaire in a .doc file, Google Doc, or similar format. Spreadsheet formats (.xls, Google Sheets, etc.) will be subject to additional fees and further scoping by Qualtrics. Assumptions: After initial survey recommendations are shared, Customer may request up to 3 rounds of iteration for review (Customer marked-up feedback on question content, response options, or logic that impacts 5 or more questions) Estimated Timing: 3-5 business days | H3: Qualtrics will provide one (1) survey review for Customer. Such survey review will include: Up to 60 questions (individual statements in a matrix or similar format each count as a question) Such survey review will not include: Technical review or testing Survey build or survey programming edits Delivery Team Responsibilities: Provide methodological expertise on best design practices and technical expertise on what is feasible in the platform. Conduct Quality Assurance (QA) for Customer's survey design. Share recommendations for Customer review. Customer Responsibilities: Provide a fully written out questionnaire, including demographics and screener questions. Bullets or partially written questions will require design services and an additional cost. Provide the questionnaire in a .doc file, Google Doc, or similar format. Spreadsheet formats (.xls, Google Sheets, etc.) will require additional scoping and costs. Answer questions and clarify requirements as needed during project. Review Qualtrics survey recommendations and provide consolidated feedback from relevant stakeholders. Provide written sign off on final survey design. Assumptions: After initial survey recommendations are shared, Customer may request up to 2 rounds of iteration for review (Customer marked-up feedback on question content, response options, or logic that impacts 5 or more questions). | I3: Aug 18, 22: Price updated. Refer to RX Cost Normalization. | J3: ='Ad-Hoc | Design and Build'!$D11 -> 3100 | K3: ='Ad-Hoc | Design and Build'!$D12 -> 3000 | O3: Ali H. & Adam P. | P3: Conor C. & James P. | Q3: Sam B. | R3: per service | T3: Yes | U3: Yes | V3: Yes | AA3: =ROUNDUP(AN3,-1) -> 630 | AB3: 0.76 | AC3: 2 | AD3: 1 | AE3: Build Services template | AF3: Internal | AG3: Vendor | AI3: 1 | AK3: 6 | AL3: 1 | AN3: =(AH3*'Staff Rates (Internal)'!B$2)+(AI3*'Staff Rates (Internal)'!B$3)+(AJ3*'Staff Rates (Internal)'!B$4)+(AK3*'Staff Rates (Internal)'!B$5)+(AL3*'Staff Rates (Internal)'!B$6)+(AM3*'Staff Rates (Internal)'!B$7) -> 622.5 | AO3: =(AH3*'Staff Rates (External)'!B$2)+(AI3*'Staff Rates (External)'!B$3)+(AJ3*'Staff Rates (External)'!B$4)+(AK3*'Staff Rates (External)'!B$5)+(AL3*'Staff Rates (External)'!B$6)+(AM3*'Staff Rates (External)'!B$7) -> 2100 | AR3: Y2 Analytics | AS3: Strop | CC3: =C3 -> Survey Review and Consultation | CD3: =average(CE3:CO3) -> 2.1818182 | CE3: 3 | CF3: 3 | CG3: 2 | CH3: 3 | CI3: 2 | CJ3: 3 | CK3: 2 | CL3: 3 | CM3: 1 | CN3: 1 | CO3: 1
A4: RS | B4: Ad-Hoc | Design and Build | C4: Survey Review and Consultation | D4: Advanced | E4: RSSurveyRevConsult | F4: =E4&" - "&D4 -> RSSurveyRevConsult - Advanced | G4: ='Ad-Hoc | Design and Build'!$E10 -> Qualtrics will review one (1) survey for Customer. Such survey review will include: Up to 100 questions (each individual statement in a matrix or similar format counts as a question) Unless otherwise agreed, such survey review will not include: Technical review or testing Survey build or survey programming edits Delivery Team Responsibilities: If necessary, conduct kick-off call to discuss research objectives. Provide methodological expertise on best design practices and technical expertise on what is feasible in the platform. Conduct Quality Assurance (QA) for Customer's survey design. Share recommendations for Customer review. Customer Responsibilities: Provide a fully written out questionnaire, including demographics and screener questions. Bullets or partially written questions will be subject to additional fees and further scoping by Qualtrics. Provide the questionnaire in a .doc file, Google Doc, or similar format. Spreadsheet formats (.xls, Google Sheets, etc.) will be subject to additional fees and further scoping by Qualtrics. Assumptions: After initial survey recommendations are shared, Customer may request up to 4 rounds of iteration for review (Customer marked-up feedback on question content, response options, or logic that impacts 5 or more questions) Estimated Timing: 5-7 business days | H4: Qualtrics will provide one (1) survey review for Customer. Such survey review will include: Up to 100 questions (individual statements in a matrix or similar format each count as a question) Such survey review will not include: Technical review or testing Survey build or survey programming edits Delivery Team Responsibilities: Provide methodological expertise on best design practices and technical expertise on what is feasible in the platform. Conduct Quality Assurance (QA) for Customer's survey design. Share recommendations for Customer review. Customer Responsibilities: Provide a fully written out questionnaire, including demographics and screener questions. Bullets or partially written questions will require design services and an additional cost. Provide the questionnaire in a .doc file, Google Doc, or similar format. Spreadsheet formats (.xls, Google Sheets, etc.) will require additional scoping and costs. Answer questions and clarify requirements as needed during project. Review Qualtrics survey recommendations and provide consolidated feedback from relevant stakeholders. Provide written sign off on final survey design. Assumptions: After initial survey recommendations are shared, Customer may request up to 4 rounds of iteration for review (Customer marked-up feedback on question content, response options, or logic that impacts 5 or more questions). | I4: Aug 18, 22: Price updated. Refer to RX Cost Normalization. | J4: ='Ad-Hoc | Design and Build'!$E11 -> 5100 | K4: ='Ad-Hoc | Design and Build'!$E12 -> 5000 | O4: Ali H. & Adam P. | P4: Conor C. & James P. | Q4: Sam B. | R4: per service | T4: Yes | U4: Yes | V4: Yes | AA4: =ROUNDUP(AN4,-1) -> 1350 | AB4: 0.76 | AC4: 2 | AD4: 1 | AE4: Build Services template | AF4: Internal | AG4: Vendor | AI4: 1 | AK4: 10 | AL4: 4 | AN4: =(AH4*'Staff Rates (Internal)'!B$2)+(AI4*'Staff Rates (Internal)'!B$3)+(AJ4*'Staff Rates (Internal)'!B$4)+(AK4*'Staff Rates (Internal)'!B$5)+(AL4*'Staff Rates (Internal)'!B$6)+(AM4*'Staff Rates (Internal)'!B$7) -> 1342.5 | AO4: =(AH4*'Staff Rates (External)'!B$2)+(AI4*'Staff Rates (External)'!B$3)+(AJ4*'Staff Rates (External)'!B$4)+(AK4*'Staff Rates (External)'!B$5)+(AL4*'Staff Rates (External)'!B$6)+(AM4*'Staff Rates (External)'!B$7) -> 4150 | AR4: Y2 Analytics | AS4: Strop | CC4: =C4 -> Survey Review and Consultation | CD4: =average(CE4:CO4) -> 2.1818182 | CE4: 3 | CF4: 3 | CG4: 2 | CH4: 3 | CI4: 2 | CJ4: 3 | CK4: 2 | CL4: 3 | CM4: 1 | CN4: 1 | CO4: 1
A5: RS | B5: Ad-Hoc | Design and Build | C5: Survey Review and Consultation | D5: Custom | E5: RSSurveyRevConsult | F5: =E5&" - "&D5 -> RSSurveyRevConsult - Custom | G5: ='Ad-Hoc | Design and Build'!$F10 -> Custom quote for multiple surveys, review of a translated survey, or advanced consultation needs | J5: ='Ad-Hoc | Design and Build'!$F11 -> Custom Quote | R5: per service | T5: Yes | U5: Yes | V5: Yes | AA5: =ROUNDUP(AN5,-1) -> 70 | AB5: 0.76 | AC5: 2 | AD5: 1 | AE5: Build Services template | AF5: Internal | AG5: Vendor | AI5: 1 | AN5: =(AH5*'Staff Rates (Internal)'!B$2)+(AI5*'Staff Rates (Internal)'!B$3)+(AJ5*'Staff Rates (Internal)'!B$4)+(AK5*'Staff Rates (Internal)'!B$5)+(AL5*'Staff Rates (Internal)'!B$6)+(AM5*'Staff Rates (Internal)'!B$7) -> 67.5 | AO5: =(AH5*'Staff Rates (External)'!B$2)+(AI5*'Staff Rates (External)'!B$3)+(AJ5*'Staff Rates (External)'!B$4)+(AK5*'Staff Rates (External)'!B$5)+(AL5*'Staff Rates (External)'!B$6)+(AM5*'Staff Rates (External)'!B$7) -> 250 | AR5: Y2 Analytics | AS5: Strop | CC5: =C5 -> Survey Review and Consultation | CD5: =average(CE5:CO5) -> 1.8181818 | CE5: 1 | CF5: 1 | CG5: 2 | CH5: 3 | CI5: 2 | CJ5: 3 | CK5: 2 | CL5: 3 | CM5: 1 | CN5: 1 | CO5: 1
A6: RS | B6: Ad-Hoc | Design and Build | C6: Survey Design & Build | D6: Standard | E6: RSSurveyDesignBuild | F6: =E6&" - "&D6 -> RSSurveyDesignBuild - Standard | G6: ='Ad-Hoc | Design and Build'!$C15 -> Includes design and programming for: 1 survey in English Up to 30 questions or elements (Embedded Data, hidden variables, individual statements in a matrix or similar format) Light survey flow logic (fewer than 10 survey flow elements such as randomizers and branches) Up to 2 rounds of iteration for design (one round of customer marked-up feedback on question content, response options, or logic that impacts 5 or more questions) Assumptions: After the Qualtrics test link is shared, the customer may request up to a total of 2 hours of additional programming changes (new wording, logic, etc.). Changes after this point will require additional scoping and fees. All corrections (programmer errors) will be addressed and do not count toward these programming hours. Only existing platform functionality will be used. Requests that are outside of platform functionality or require custom coding may require additional scoping and cost. The customer is responsible for providing any images or video files required in the correct format, resolution, dimensions, and file size. Qualtrics will not source or modify any files. No manual implementation of customer-provided translations is included. Estimated Timing: ~4 weeks (1 week for design, 1 week for client review, 1 week for programming, 1 week for client review) | H6: Qualtrics will provide one (1) survey design and one (1) survey build for Customer. Such survey design and build will include: 1 survey in English Up to 30 questions or elements (Embedded Data, hidden variables, individual statements in a matrix or similar format) Light survey flow logic (fewer than 10 survey flow elements such as randomizers and branches) Delivery Team Responsibilities: Provide methodological expertise on best design practices and technical expertise on what is feasible in the platform. Draft survey design in English. Conduct Quality Assurance (QA) for survey design. Provide drafted survey in .doc format for Customer review. Implement Customer feedback. After receiving written sign off on design, program the survey in Qualtrics in English. Ensure compatibility with fielding and reporting needs as possible. Conduct QA to ensure correct functionality per survey design. Provide programmed survey link to Customer for User Acceptance Testing (UAT). Implement Customer UAT feedback. Customer Responsibilities: Provide design inputs requested by Qualtrics related to study goals. Provide any images or video files required in the correct format, resolution, dimensions, and file size. Qualtrics will not source or modify any files. Answer questions and clarify requirements as needed during project. Review survey design and provide consolidated feedback from relevant stakeholders. Provide written sign off on final survey design. Perform UAT of the programming survey link and provide consolidated feedback from relevant stakeholders. Provide written sign off on final survey build. Assumptions: Such survey design and build will not include manual implementation of customer-provided translations. Only existing platform functionality will be used. Requests that are outside of platform functionality or require custom coding will be subject to additional fees and further scoping by Qualtrics. After initial survey draft is shared, Customer may request up to 2 rounds of iteration for design (Customer marked-up feedback on question content, response options, or logic that impacts 5 or more questions). Survey programming will not begin until Customer has provided written sign off on the survey design. After the Qualtrics survey test link is shared, Customer may request up to 2 rounds of additional programming changes (new wording, logic, etc.), which may not exceed more than 2 hours of programmer time to implement. Changes requested after this point will be subject to additional fees and further scoping by Qualtrics. All corrections (programmer errors) will be addressed and do not count toward these programming hours. | J6: ='Ad-Hoc | Design and Build'!$C16 -> 8000 | O6: Ali H. & Adam P. | P6: Conor C. & James P. | Q6: Sam B. Suggest a shorter 'standard' timeframe. 4 weeks is too long. Maybe 1 week for design, 1 week for build and test. Rest is up to client to expedite | R6: per service | T6: Yes | U6: Yes | V6: Yes | AA6: =ROUNDUP(AN6,-1) -> 1900 | AB6: 0.76 | AC6: 2 | AD6: 1 | AE6: Build Services template | AF6: Internal | AG6: Vendor w/ RX Review | AI6: 1 | AJ6: 22 | AL6: 6 | AN6: =(AH6*'Staff Rates (Internal)'!B$2)+(AI6*'Staff Rates (Internal)'!B$3)+(AJ6*'Staff Rates (Internal)'!B$4)+(AK6*'Staff Rates (Internal)'!B$5)+(AL6*'Staff Rates (Internal)'!B$6)+(AM6*'Staff Rates (Internal)'!B$7) -> 1891.5 | AO6: =(AH6*'Staff Rates (External)'!B$2)+(AI6*'Staff Rates (External)'!B$3)+(AJ6*'Staff Rates (External)'!B$4)+(AK6*'Staff Rates (External)'!B$5)+(AL6*'Staff Rates (External)'!B$6)+(AM6*'Staff Rates (External)'!B$7) -> 7850 | AR6: Y2 Analytics | AS6: Strop | AX6: Yes | CC6: =C6 -> Survey Design & Build | CD6: =average(CE6:CO6) -> 2.1818182 | CE6: 3 | CF6: 3 | CG6: 2 | CH6: 3 | CI6: 2 | CJ6: 3 | CK6: 2 | CL6: 3 | CM6: 1 | CN6: 1 | CO6: 1
A7: RS | B7: Ad-Hoc | Design and Build | C7: Survey Design & Build | D7: Standard Plus | F7: =E7&" - "&D7 -> - Standard Plus | G7: ='Ad-Hoc | Design and Build'!$D15 -> Includes design and programming for: 1 survey in English Up to 60 questions or elements (Embedded Data, hidden variables, individual statements in a matrix or similar format) Moderate survey flow logic (fewer than 50 survey flow elements such as randomizers and branches) Up to 3 rounds of iteration for design (one round of customer marked-up feedback on question content, response options, or logic that impacts 5 or more questions) Assumptions: After the Qualtrics test link is shared, the customer may request up to a total of 3 hours of additional programming changes (new wording, logic, etc.). Changes after this point will require additional scoping and fees. All corrections (programmer errors) will be addressed and do not count toward these programming hours. Only existing platform functionality will be used. Requests that are outside of platform functionality or require custom coding may require additional scoping and cost. The customer is responsible for providing any images or video files required in the correct format, resolution, dimensions, and file size. Qualtrics will not source or modify any files. No manual implementation of customer-provided translations is included. Estimated Timing: ~4 weeks (1 week for design, 1 week for client review, 1 week for programming, 1 week for client review) | H7: Qualtrics will provide one (1) survey design and one (1) survey build for Customer. Such survey design and build will include: 1 survey in English Up to 60 questions or elements (Embedded Data, hidden variables, individual statements in a matrix or similar format) Moderate survey flow logic (fewer than 50 survey flow elements such as randomizers and branches) Delivery Team Responsibilities: Provide methodological expertise on best design practices and technical expertise on what is feasible in the platform. Draft survey design in English. Conduct Quality Assurance (QA) for survey design. Provide drafted survey in .doc format for Customer review. Implement Customer feedback. After receiving written sign off on design, program the survey in Qualtrics in English. Ensure compatibility with fielding and reporting needs as possible. Conduct QA to ensure correct functionality per survey design. Provide programmed survey link to Customer for User Acceptance Testing (UAT). Implement Customer UAT feedback. Customer Responsibilities: Provide design inputs requested by Qualtrics related to study goals. Provide any images or video files required in the correct format, resolution, dimensions, and file size. Qualtrics will not source or modify any files. Answer questions and clarify requirements as needed during project. Review survey design and provide consolidated feedback from relevant stakeholders. Provide written sign off on final survey design. Perform UAT of the programming survey link and provide consolidated feedback from relevant stakeholders. Provide written sign off on final survey build. Assumptions: Such survey design and build will not include manual implementation of customer-provided translations. Only existing platform functionality will be used. Requests that are outside of platform functionality or require custom coding will be subject to additional fees and further scoping by Qualtrics. After initial survey draft is shared, Customer may request up to 3 rounds of iteration for design (Customer marked-up feedback on question content, response options, or logic that impacts 5 or more questions). Survey programming will not begin until Customer has provided written sign off on the survey design. After the Qualtrics survey test link is shared, Customer may request up to 3 rounds of additional programming changes (new wording, logic, etc.), which may not exceed more than 3 hours of programmer time to implement. Changes requested after this point will be subject to additional fees and further scoping by Qualtrics. All corrections (programmer errors) will be addressed and do not count toward these programming hours. | J7: ='Ad-Hoc | Design and Build'!$D16 -> 11500 | O7: Ali H. & Adam P. | P7: Conor C. & James P. | Q7: Sam B. As above | R7: per service | T7: Yes | U7: Yes | V7: Yes | AA7: =ROUNDUP(AN7,-1) -> 2860 | AB7: 0.76 | AC7: 2 | AD7: 1 | AE7: Build Services template | AF7: Internal | AG7: Vendor w/ RX Review | AI7: 2 | AJ7: 4 | AK7: 20 | AL7: 8 | AN7: =(AH7*'Staff Rates (Internal)'!B$2)+(AI7*'Staff Rates (Internal)'!B$3)+(AJ7*'Staff Rates (Internal)'!B$4)+(AK7*'Staff Rates (Internal)'!B$5)+(AL7*'Staff Rates (Internal)'!B$6)+(AM7*'Staff Rates (Internal)'!B$7) -> 2853 | AO7: =(AH7*'Staff Rates (External)'!B$2)+(AI7*'Staff Rates (External)'!B$3)+(AJ7*'Staff Rates (External)'!B$4)+(AK7*'Staff Rates (External)'!B$5)+(AL7*'Staff Rates (External)'!B$6)+(AM7*'Staff Rates (External)'!B$7) -> 9300 | AR7: Y2 Analytics | AS7: Strop | AY7: Yes | BB7: Yes | BF7: Yes | BJ7: Yes | BK7: Yes | CC7: =C7 -> Survey Design & Build | CD7: =average(CE7:CO7) -> 2.1818182 | CE7: 3 | CF7: 3 | CG7: 2 | CH7: 3 | CI7: 2 | CJ7: 3 | CK7: 2 | CL7: 3 | CM7: 1 | CN7: 1 | CO7: 1
A8: RS | B8: Ad-Hoc | Design and Build | C8: Survey Design & Build | D8: Advanced | E8: RSSurveyDesignBuild | F8: =E8&" - "&D8 -> RSSurveyDesignBuild - Advanced | G8: ='Ad-Hoc | Design and Build'!$E15 -> Includes design and programming for: 1 survey in English Up to 100 questions or elements (Embedded Data, hidden variables, individual statements in a matrix or similar format) Heavy survey flow logic (fewer than 100 survey flow elements such as randomizers and branches) Up to 4 rounds of iteration for design (one round of customer marked-up feedback on question content, response options, or logic that impacts 5 or more questions) Assumptions: After the Qualtrics test link is shared, the customer may request up to a total of 4 hours of additional programming changes (new wording, logic, etc.). Changes after this point will require additional scoping and fees. All corrections (programmer errors) will be addressed and do not count toward these programming hours. Only existing platform functionality will be used. Requests that are outside of platform functionality or require custom coding may require additional scoping and cost. The customer is responsible for providing any images or video files required in the correct format, resolution, dimensions, and file size. Qualtrics will not source or modify any files. No manual implementation of customer-provided translations is included. Estimated Timing: ~5 weeks (1 week for design, 1 week for client review, 2 weeks for programming, 1 week for client review) | H8: Qualtrics will provide one (1) survey design and one (1) survey build for Customer. Such survey design and build will include: 1 survey in English Up to 100 questions or elements (Embedded Data, hidden variables, individual statements in a matrix or similar format) Heavy survey flow logic (fewer than 100 survey flow elements such as randomizers and branches) Delivery Team Responsibilities: Provide methodological expertise on best design practices and technical expertise on what is feasible in the platform. Draft survey design in English. Conduct Quality Assurance (QA) for survey design. Provide drafted survey in .doc format for Customer review. Implement Customer feedback. After receiving written sign off on design, program the survey in Qualtrics in English. Ensure compatibility with fielding and reporting needs as possible. Conduct QA to ensure correct functionality per survey design. Provide programmed survey link to Customer for User Acceptance Testing (UAT). Implement Customer UAT feedback. Customer Responsibilities: Provide design inputs requested by Qualtrics related to study goals. Provide any images or video files required in the correct format, resolution, dimensions, and file size. Qualtrics will not source or modify any files. Answer questions and clarify requirements as needed during project. Review survey design and provide consolidated feedback from relevant stakeholders. Provide written sign off on final survey design. Perform UAT of the programming survey link and provide consolidated feedback from relevant stakeholders. Provide written sign off on final survey build. Assumptions: Such survey design and build will not include manual implementation of customer-provided translations. Only existing platform functionality will be used. Requests that are outside of platform functionality or require custom coding will be subject to additional fees and further scoping by Qualtrics. After initial survey draft is shared, Customer may request up to 4 rounds of iteration for design (Customer marked-up feedback on question content, response options, or logic that impacts 5 or more questions). Survey programming will not begin until Customer has provided written sign off on the survey design. After the Qualtrics survey test link is shared, Customer may request up to 4 rounds of additional programming changes (new wording, logic, etc.), which may not exceed more than 4 hours of programmer time to implement. Changes requested after this point will be subject to additional fees and further scoping by Qualtrics. All corrections (programmer errors) will be addressed and do not count toward these programming hours. | J8: ='Ad-Hoc | Design and Build'!$E16 -> 14000 | O8: Ali H. & Adam P. | P8: Conor C. & James P. | Q8: Sam B. As above, but 1.5-2 weeks for programming seems ok | R8: per service | T8: Yes | U8: Yes | V8: Yes | AA8: =ROUNDUP(AN8,-1) -> 4220 | AB8: 0.76 | AC8: 2 | AD8: 1 | AE8: Build Services template | AF8: Internal | AG8: Vendor w/ RX Review | AI8: 4 | AJ8: 6 | AK8: 28 | AL8: 12 | AN8: =(AH8*'Staff Rates (Internal)'!B$2)+(AI8*'Staff Rates (Internal)'!B$3)+(AJ8*'Staff Rates (Internal)'!B$4)+(AK8*'Staff Rates (Internal)'!B$5)+(AL8*'Staff Rates (Internal)'!B$6)+(AM8*'Staff Rates (Internal)'!B$7) -> 4212 | AO8: =(AH8*'Staff Rates (External)'!B$2)+(AI8*'Staff Rates (External)'!B$3)+(AJ8*'Staff Rates (External)'!B$4)+(AK8*'Staff Rates (External)'!B$5)+(AL8*'Staff Rates (External)'!B$6)+(AM8*'Staff Rates (External)'!B$7) -> 13700 | AR8: Y2 Analytics | AS8: Strop | AZ8: Yes | BC8: Yes | BD8: Yes | BG8: Yes | BH8: Yes | BL8: Yes | BZ8: Yes | CC8: =C8 -> Survey Design & Build | CD8: =average(CE8:CO8) -> 2.1818182 | CE8: 3 | CF8: 3 | CG8: 2 | CH8: 3 | CI8: 2 | CJ8: 3 | CK8: 2 | CL8: 3 | CM8: 1 | CN8: 1 | CO8: 1
A9: RS | B9: Ad-Hoc | Design and Build | C9: Survey Design & Build | D9: Custom | E9: RSSurveyDesignBuild | F9: =E9&" - "&D9 -> RSSurveyDesignBuild - Custom | G9: ='Ad-Hoc | Design and Build'!$F15 -> Custom quote for survey with over 100 questions or elements, email or other triggers built in, advanced coding (javascript, API calls, HTML, etc.), multiple surveys, advanced analytics (MaxDiff, etc.) | J9: ='Ad-Hoc | Design and Build'!$F16 -> Custom Quote | R9: per service | T9: Yes | U9: Yes | V9: Yes | AA9: =ROUNDUP(AN9,-1) -> 270 | AB9: 0.76 | AC9: 2 | AD9: 1 | AE9: Build Services template | AF9: Internal | AG9: Vendor w/ RX Review | AI9: 4 | AN9: =(AH9*'Staff Rates (Internal)'!B$2)+(AI9*'Staff Rates (Internal)'!B$3)+(AJ9*'Staff Rates (Internal)'!B$4)+(AK9*'Staff Rates (Internal)'!B$5)+(AL9*'Staff Rates (Internal)'!B$6)+(AM9*'Staff Rates (Internal)'!B$7) -> 270 | AO9: =(AH9*'Staff Rates (External)'!B$2)+(AI9*'Staff Rates (External)'!B$3)+(AJ9*'Staff Rates (External)'!B$4)+(AK9*'Staff Rates (External)'!B$5)+(AL9*'Staff Rates (External)'!B$6)+(AM9*'Staff Rates (External)'!B$7) -> 1000 | AR9: Y2 Analytics | AS9: Strop | BA9: Yes | BE9: Yes | BI9: Yes | BM9: Yes | CA9: Yes | CC9: =C9 -> Survey Design & Build | CD9: =average(CE9:CO9) -> 1.8181818 | CE9: 1 | CF9: 1 | CG9: 2 | CH9: 3 | CI9: 2 | CJ9: 3 | CK9: 2 | CL9: 3 | CM9: 1 | CN9: 1 | CO9: 1
A10: RS | B10: Ad-Hoc | Design and Build | C10: Survey Design (without Build) | D10: Standard | E10: RSSurveyDesign | F10: =E10&" - "&D10 -> RSSurveyDesign - Standard | G10: ='Ad-Hoc | Design and Build'!$C19 -> Includes design for: 1 survey in English Up to 30 questions or elements (Embedded Data, hidden variables, individual statements in a matrix or similar format) Light survey flow logic (fewer than 10 survey flow elements such as randomizers, blocks, and branches) noted in document Up to 2 rounds of iteration (one round of customer marked-up feedback on question content, response options, or logic that impacts 5 or more questions) Estimated Timing: ~2 weeks (1 week for design, 1 week for client review) | H10: Qualtrics will provide one (1) survey design for Customer. Such survey design will include: 1 survey in English Up to 30 questions or elements (Embedded Data, hidden variables, individual statements in a matrix or similar format) Light survey flow logic (fewer than 10 survey flow elements such as randomizers and branches) Such survey design will not include: Technical review or testing Survey build or survey programming edits Delivery Team Responsibilities: Provide methodological expertise on best design practices and technical expertise on what is feasible in the platform. Draft survey design in English. Conduct Quality Assurance (QA) for survey design. Provide drafted survey in .doc format for Customer review. Implement Customer feedback. Customer Responsibilities: Provide design inputs requested by Qualtrics related to study goals. Provide any images or video files required in the correct format, resolution, dimensions, and file size. Qualtrics will not source or modify any files. Answer questions and clarify requirements as needed during project. Review survey design and provide consolidated feedback from relevant stakeholders. Provide written sign off on final survey design. Assumptions: After initial survey draft is shared, Customer may request up to 2 rounds of iteration for design (Customer marked-up feedback on question content, response options, or logic that impacts 5 or more questions). | I10: Aug 18, 22: Price updated. Refer to RX Cost Normalization. | J10: ='Ad-Hoc | Design and Build'!$C20 -> 6100 | O10: Ali H. & Adam P. | P10: Conor C. & James P. | Q10: Sam B. | R10: per service | T10: No | U10: No | V10: No | AA10: =ROUNDUP(AN10,-1) -> 1490 | AB10: 0.76 | AC10: 2 | AD10: 1 | AE10: Build Services template | AF10: Internal | AG10: Vendor w/ RX Review | AI10: 1 | AJ10: 16 | AL10: 5 | AN10: =(AH10*'Staff Rates (Internal)'!B$2)+(AI10*'Staff Rates (Internal)'!B$3)+(AJ10*'Staff Rates (Internal)'!B$4)+(AK10*'Staff Rates (Internal)'!B$5)+(AL10*'Staff Rates (Internal)'!B$6)+(AM10*'Staff Rates (Internal)'!B$7) -> 1489.5 | AO10: =(AH10*'Staff Rates (External)'!B$2)+(AI10*'Staff Rates (External)'!B$3)+(AJ10*'Staff Rates (External)'!B$4)+(AK10*'Staff Rates (External)'!B$5)+(AL10*'Staff Rates (External)'!B$6)+(AM10*'Staff Rates (External)'!B$7) -> 6000 | AR10: Y2 Analytics | AS10: Strop | AX10: Yes | CC10: =C10 -> Survey Design (without Build) | CD10: =average(CE10:CO10) -> 2 | CE10: 3 | CF10: 3 | CG10: 2 | CH10: 1 | CI10: 2 | CJ10: 3 | CK10: 2 | CL10: 3 | CM10: 1 | CN10: 1 | CO10: 1
A11: RS | B11: Ad-Hoc | Design and Build | C11: Survey Design (without Build) | D11: Standard Plus | E11: RSSurveyDesign | F11: =E11&" - "&D11 -> RSSurveyDesign - Standard Plus | G11: ='Ad-Hoc | Design and Build'!$D19 -> Includes design for: 1 survey in English Up to 60 questions or elements (Embedded Data, hidden variables, individual statements in a matrix or similar format) Moderate survey flow logic (fewer than 50 survey flow elements such as randomizers, blocks, and branches) noted in document Up to 3 rounds of iteration (one round of customer marked-up feedback on question content, response options, or logic that impacts 5 or more questions) Estimated Timing: ~2 weeks (1 week for design, 1 week for client review) | H11: Qualtrics will provide one (1) survey design for Customer. Such survey design will include: 1 survey in English Up to 60 questions or elements (Embedded Data, hidden variables, individual statements in a matrix or similar format) Moderate survey flow logic (fewer than 50 survey flow elements such as randomizers and branches) Such survey design will not include: Technical review or testing Survey build or survey programming edits Delivery Team Responsibilities: Provide methodological expertise on best design practices and technical expertise on what is feasible in the platform. Draft survey design in English. Conduct Quality Assurance (QA) for survey design. Provide drafted survey in .doc format for Customer review. Implement Customer feedback. Customer Responsibilities: Provide design inputs requested by Qualtrics related to study goals. Provide any images or video files required in the correct format, resolution, dimensions, and file size. Qualtrics will not source or modify any files. Answer questions and clarify requirements as needed during project. Review survey design and provide consolidated feedback from relevant stakeholders. Provide written sign off on final survey design. Assumptions: After initial survey draft is shared, Customer may request up to 3 rounds of iteration for design (Customer marked-up feedback on question content, response options, or logic that impacts 5 or more questions). | I11: Aug 18, 22: Price updated. Refer to RX Cost Normalization. | J11: ='Ad-Hoc | Design and Build'!$D20 -> 8100 | O11: Ali H. & Adam P. | P11: Conor C. & James P. | Q11: Sam B. | R11: per service | T11: No | U11: No | V11: No | AA11: =ROUNDUP(AN11,-1) -> 1900 | AB11: 0.76 | AC11: 2 | AD11: 1 | AE11: Build Services template | AF11: Internal | AG11: Vendor w/ RX Review | AI11: 2 | AJ11: 2 | AK11: 16 | AL11: 4 | AN11: =(AH11*'Staff Rates (Internal)'!B$2)+(AI11*'Staff Rates (Internal)'!B$3)+(AJ11*'Staff Rates (Internal)'!B$4)+(AK11*'Staff Rates (Internal)'!B$5)+(AL11*'Staff Rates (Internal)'!B$6)+(AM11*'Staff Rates (Internal)'!B$7) -> 1899 | AO11: =(AH11*'Staff Rates (External)'!B$2)+(AI11*'Staff Rates (External)'!B$3)+(AJ11*'Staff Rates (External)'!B$4)+(AK11*'Staff Rates (External)'!B$5)+(AL11*'Staff Rates (External)'!B$6)+(AM11*'Staff Rates (External)'!B$7) -> 6400 | AR11: Y2 Analytics | AS11: Strop | AY11: Yes | BB11: Yes | BF11: Yes | BJ11: Yes | BK11: Yes | CC11: =C11 -> Survey Design (without Build) | CD11: =average(CE11:CO11) -> 2 | CE11: 3 | CF11: 3 | CG11: 2 | CH11: 1 | CI11: 2 | CJ11: 3 | CK11: 2 | CL11: 3 | CM11: 1 | CN11: 1 | CO11: 1
